{"data": {"request": [{"type": "City", "query": "Boulemane, Morocco"}], "weather": [{"date": "2021-02-17", "astronomy": [{"sunrise": "08:01 AM", "sunset": "07:06 PM", "moonrise": "11:14 AM", "moonset": "No moonset", "moon_phase": "Waxing Crescent", "moon_illumination": "36"}], "maxtempC": "17", "maxtempF": "63", "mintempC": "6", "mintempF": "42", "avgtempC": "12", "avgtempF": "54", "totalSnow_cm": "0.0", "sunHour": "11.1", "uvIndex": "4", "hourly": [{"time": "0", "tempC": "9", "tempF": "49", "windspeedMiles": "3", "windspeedKmph": "4", "winddirDegree": "154", "winddir16Point": "SSE", "weatherCode": "113", "weatherIconUrl": [{"value": "http://cdn.worldweatheronline.com/images/wsymbols01_png_64/wsymbol_0008_clear_sky_night.png"}], "weatherDesc": [{"value": "Clear"}], "lang_fr": [{"value": "Clair"}], "precipMM": "0.0", "precipInches": "0.0", "humidity": "52", "visibility": "10", "visibilityMiles": "6", "pressure": "1025", "pressureInches": "30", "cloudcover": "0", "HeatIndexC": "9", "HeatIndexF": "49", "DewPointC": "0", "DewPointF": "32", "WindChillC": "9", "WindChillF": "49", "WindGustMiles": "6", "WindGustKmph": "9", "FeelsLikeC": "9", "FeelsLikeF": "49", "uvIndex": "1"}, {"time": "100", "tempC": "9", "tempF": "48", "windspeedMiles": "3", "windspeedKmph": "5", "winddirDegree": "150", "winddir16Point": "SSE", "weatherCode": "113", "weatherIconUrl": [{"value": "http://cdn.worldweatheronline.com/images/wsymbols01_png_64/wsymbol_0008_clear_sky_night.png"}], "weatherDesc": [{"value": "Clear"}], "lang_fr": [{"value": "Clair"}], "precipMM": "0.0", "precipInches": "0.0", "humidity": "49", "visibility": "10", "visibilityMiles": "6", "pressure": "1025", "pressureInches": "30", "cloudcover": "0", "HeatIndexC": "9", "HeatIndexF": "48", "DewPointC": "-2", "DewPointF": "29", "WindChillC": "8", "WindChillF": "47", "WindGustMiles": "6", "WindGustKmph": "10", "FeelsLikeC": "8", "FeelsLikeF": "47", "uvIndex": "1"}, {"time": "200", "tempC": "8", "tempF": "46", "windspeedMiles": "3", "windspeedKmph": "5", "winddirDegree": "146", "winddir16Point": "SE", "weatherCode": "113", "weatherIconUrl": [{"value": "http://cdn.worldweatheronline.com/images/wsymbols01_png_64/wsymbol_0008_clear_sky_night.png"}], "weatherDesc": [{"value": "Clear"}], "lang_fr": [{"value": "Clair"}], "precipMM": "0.0", "precipInches": "0.0", "humidity": "45", "visibility": "10", "visibilityMiles": "6", "pressure": "1024", "pressureInches": "30", "cloudcover": "0", "HeatIndexC": "8", "HeatIndexF": "46", "DewPointC": "-3", "DewPointF": "26", "WindChillC": "7", "WindChillF": "45", "WindGustMiles": "6", "WindGustKmph": "10", "FeelsLikeC": "7", "FeelsLikeF": "45", "uvIndex": "1"}, {"time": "300", "tempC": "7", "tempF": "45", "windspeedMiles": "3", "windspeedKmph": "5", "winddirDegree": "142", "winddir16Point": "SE", "weatherCode": "113", "weatherIconUrl": [{"value": "http://cdn.worldweatheronline.com/images/wsymbols01_png_64/wsymbol_0008_clear_sky_night.png"}], "weatherDesc": [{"value": "Clear"}], "lang_fr": [{"value": "Clair"}], "precipMM": "0.0", "precipInches": "0.0", "humidity": "42", "visibility": "10", "visibilityMiles": "6", "pressure": "1024", "pressureInches": "30", "cloudcover": "0", "HeatIndexC": "7", "HeatIndexF": "45", "DewPointC": "-5", "DewPointF": "23", "WindChillC": "7", "WindChillF": "44", "WindGustMiles": "7", "WindGustKmph": "11", "FeelsLikeC": "7", "FeelsLikeF": "44", "uvIndex": "1"}, {"time": "400", "tempC": "7", "tempF": "44", "windspeedMiles": "4", "windspeedKmph": "6", "winddirDegree": "139", "winddir16Point": "SE", "weatherCode": "113", "weatherIconUrl": [{"value": "http://cdn.worldweatheronline.com/images/wsymbols01_png_64/wsymbol_0008_clear_sky_night.png"}], "weatherDesc": [{"value": "Clear"}], "lang_fr": [{"value": "Clair"}], "precipMM": "0.0", "precipInches": "0.0", "humidity": "41", "visibility": "10", "visibilityMiles": "6", "pressure": "1023", "pressureInches": "30", "cloudcover": "0", "HeatIndexC": "7", "HeatIndexF": "44", "DewPointC": "-6", "DewPointF": "22", "WindChillC": "6", "WindChillF": "42", "WindGustMiles": "8", "WindGustKmph": "13", "FeelsLikeC": "6", "FeelsLikeF": "42", "uvIndex": "1"}, {"time": "500", "tempC": "6", "tempF": "43", "windspeedMiles": "5", "windspeedKmph": "8", "winddirDegree": "137", "winddir16Point": "SE", "weatherCode": "113", "weatherIconUrl": [{"value": "http://cdn.worldweatheronline.com/images/wsymbols01_png_64/wsymbol_0008_clear_sky_night.png"}], "weatherDesc": [{"value": "Clear"}], "lang_fr": [{"value": "Clair"}], "precipMM": "0.0", "precipInches": "0.0", "humidity": "39", "visibility": "10", "visibilityMiles": "6", "pressure": "1023", "pressureInches": "30", "cloudcover": "0", "HeatIndexC": "6", "HeatIndexF": "43", "DewPointC": "-7", "DewPointF": "20", "WindChillC": "5", "WindChillF": "40", "WindGustMiles": "10", "WindGustKmph": "16", "FeelsLikeC": "5", "FeelsLikeF": "40", "uvIndex": "1"}, {"time": "600", "tempC": "6", "tempF": "42", "windspeedMiles": "5", "windspeedKmph": "9", "winddirDegree": "134", "winddir16Point": "SE", "weatherCode": "113", "weatherIconUrl": [{"value": "http://cdn.worldweatheronline.com/images/wsymbols01_png_64/wsymbol_0001_sunny.png"}], "weatherDesc": [{"value": "Sunny"}], "lang_fr": [{"value": "Ensoleillé"}], "precipMM": "0.0", "precipInches": "0.0", "humidity": "38", "visibility": "10", "visibilityMiles": "6", "pressure": "1023", "pressureInches": "30", "cloudcover": "0", "HeatIndexC": "6", "HeatIndexF": "42", "DewPointC": "-8", "DewPointF": "19", "WindChillC": "4", "WindChillF": "38", "WindGustMiles": "11", "WindGustKmph": "18", "FeelsLikeC": "4", "FeelsLikeF": "38", "uvIndex": "3"}, {"time": "700", "tempC": "7", "tempF": "45", "windspeedMiles": "6", "windspeedKmph": "9", "winddirDegree": "135", "winddir16Point": "SE", "weatherCode": "113", "weatherIconUrl": [{"value": "http://cdn.worldweatheronline.com/images/wsymbols01_png_64/wsymbol_0001_sunny.png"}], "weatherDesc": [{"value": "Sunny"}], "lang_fr": [{"value": "Ensoleillé"}], "precipMM": "0.0", "precipInches": "0.0", "humidity": "37", "visibility": "10", "visibilityMiles": "6", "pressure": "1023", "pressureInches": "30", "cloudcover": "0", "HeatIndexC": "7", "HeatIndexF": "45", "DewPointC": "-6", "DewPointF": "21", "WindChillC": "6", "WindChillF": "42", "WindGustMiles": "10", "WindGustKmph": "17", "FeelsLikeC": "6", "FeelsLikeF": "42", "uvIndex": "3"}, {"time": "800", "tempC": "9", "tempF": "49", "windspeedMiles": "6", "windspeedKmph": "9", "winddirDegree": "137", "winddir16Point": "SE", "weatherCode": "113", "weatherIconUrl": [{"value": "http://cdn.worldweatheronline.com/images/wsymbols01_png_64/wsymbol_0001_sunny.png"}], "weatherDesc": [{"value": "Sunny"}], "lang_fr": [{"value": "Ensoleillé"}], "precipMM": "0.0", "precipInches": "0.0", "humidity": "36", "visibility": "10", "visibilityMiles": "6", "pressure": "1023", "pressureInches": "30", "cloudcover": "0", "HeatIndexC": "9", "HeatIndexF": "49", "DewPointC": "-5", "DewPointF": "23", "WindChillC": "8", "WindChillF": "46", "WindGustMiles": "10", "WindGustKmph": "16", "FeelsLikeC": "8", "FeelsLikeF": "46", "uvIndex": "3"}, {"time": "900", "tempC": "11", "tempF": "52", "windspeedMiles": "6", "windspeedKmph": "9", "winddirDegree": "138", "winddir16Point": "SE", "weatherCode": "113", "weatherIconUrl": [{"value": "http://cdn.worldweatheronline.com/images/wsymbols01_png_64/wsymbol_0001_sunny.png"}], "weatherDesc": [{"value": "Sunny"}], "lang_fr": [{"value": "Ensoleillé"}], "precipMM": "0.0", "precipInches": "0.0", "humidity": "34", "visibility": "10", "visibilityMiles": "6", "pressure": "1023", "pressureInches": "30", "cloudcover": "0", "HeatIndexC": "11", "HeatIndexF": "52", "DewPointC": "-4", "DewPointF": "25", "WindChillC": "10", "WindChillF": "50", "WindGustMiles": "9", "WindGustKmph": "14", "FeelsLikeC": "10", "FeelsLikeF": "50", "uvIndex": "4"}, {"time": "1000", "tempC": "13", "tempF": "56", "windspeedMiles": "5", "windspeedKmph": "7", "winddirDegree": "160", "winddir16Point": "SSE", "weatherCode": "113", "weatherIconUrl": [{"value": "http://cdn.worldweatheronline.com/images/wsymbols01_png_64/wsymbol_0001_sunny.png"}], "weatherDesc": [{"value": "Sunny"}], "lang_fr": [{"value": "Ensoleillé"}], "precipMM": "0.0", "precipInches": "0.0", "humidity": "29", "visibility": "10", "visibilityMiles": "6", "pressure": "1022", "pressureInches": "30", "cloudcover": "0", "HeatIndexC": "13", "HeatIndexF": "56", "DewPointC": "-5", "DewPointF": "23", "WindChillC": "13", "WindChillF": "55", "WindGustMiles": "7", "WindGustKmph": "11", "FeelsLikeC": "13", "FeelsLikeF": "55", "uvIndex": "4"}, {"time": "1100", "tempC": "15", "tempF": "60", "windspeedMiles": "3", "windspeedKmph": "6", "winddirDegree": "183", "winddir16Point": "S", "weatherCode": "113", "weatherIconUrl": [{"value": "http://cdn.worldweatheronline.com/images/wsymbols01_png_64/wsymbol_0001_sunny.png"}], "weatherDesc": [{"value": "Sunny"}], "lang_fr": [{"value": "Ensoleillé"}], "precipMM": "0.0", "precipInches": "0.0", "humidity": "24", "visibility": "10", "visibilityMiles": "6", "pressure": "1022", "pressureInches": "30", "cloudcover": "0", "HeatIndexC": "15", "HeatIndexF": "60", "DewPointC": "-6", "DewPointF": "22", "WindChillC": "15", "WindChillF": "59", "WindGustMiles": "5", "WindGustKmph": "7", "FeelsLikeC": "15", "FeelsLikeF": "59", "uvIndex": "5"}, {"time": "1200", "tempC": "17", "tempF": "63", "windspeedMiles": "2", "windspeedKmph": "4", "winddirDegree": "205", "winddir16Point": "SSW", "weatherCode": "113", "weatherIconUrl": [{"value": "http://cdn.worldweatheronline.com/images/wsymbols01_png_64/wsymbol_0001_sunny.png"}], "weatherDesc": [{"value": "Sunny"}], "lang_fr": [{"value": "Ensoleillé"}], "precipMM": "0.0", "precipInches": "0.0", "humidity": "19", "visibility": "10", "visibilityMiles": "6", "pressure": "1021", "pressureInches": "30", "cloudcover": "0", "HeatIndexC": "17", "HeatIndexF": "63", "DewPointC": "-6", "DewPointF": "21", "WindChillC": "17", "WindChillF": "63", "WindGustMiles": "2", "WindGustKmph": "4", "FeelsLikeC": "17", "FeelsLikeF": "63", "uvIndex": "5"}, {"time": "1300", "tempC": "17", "tempF": "62", "windspeedMiles": "4", "windspeedKmph": "7", "winddirDegree": "238", "winddir16Point": "WSW", "weatherCode": "113", "weatherIconUrl": [{"value": "http://cdn.worldweatheronline.com/images/wsymbols01_png_64/wsymbol_0001_sunny.png"}], "weatherDesc": [{"value": "Sunny"}], "lang_fr": [{"value": "Ensoleillé"}], "precipMM": "0.0", "precipInches": "0.0", "humidity": "22", "visibility": "10", "visibilityMiles": "6", "pressure": "1020", "pressureInches": "30", "cloudcover": "0", "HeatIndexC": "17", "HeatIndexF": "62", "DewPointC": "-5", "DewPointF": "23", "WindChillC": "17", "WindChillF": "62", "WindGustMiles": "5", "WindGustKmph": "7", "FeelsLikeC": "17", "FeelsLikeF": "62", "uvIndex": "5"}, {"time": "1400", "tempC": "16", "tempF": "61", "windspeedMiles": "6", "windspeedKmph": "10", "winddirDegree": "271", "winddir16Point": "W", "weatherCode": "113", "weatherIconUrl": [{"value": "http://cdn.worldweatheronline.com/images/wsymbols01_png_64/wsymbol_0001_sunny.png"}], "weatherDesc": [{"value": "Sunny"}], "lang_fr": [{"value": "Ensoleillé"}], "precipMM": "0.0", "precipInches": "0.0", "humidity": "26", "visibility": "10", "visibilityMiles": "6", "pressure": "1019", "pressureInches": "30", "cloudcover": "0", "HeatIndexC": "16", "HeatIndexF": "61", "DewPointC": "-4", "DewPointF": "26", "WindChillC": "16", "WindChillF": "61", "WindGustMiles": "7", "WindGustKmph": "11", "FeelsLikeC": "16", "FeelsLikeF": "61", "uvIndex": "5"}, {"time": "1500", "tempC": "16", "tempF": "60", "windspeedMiles": "8", "windspeedKmph": "13", "winddirDegree": "304", "winddir16Point": "NW", "weatherCode": "113", "weatherIconUrl": [{"value": "http://cdn.worldweatheronline.com/images/wsymbols01_png_64/wsymbol_0001_sunny.png"}], "weatherDesc": [{"value": "Sunny"}], "lang_fr": [{"value": "Ensoleillé"}], "precipMM": "0.0", "precipInches": "0.0", "humidity": "29", "visibility": "10", "visibilityMiles": "6", "pressure": "1019", "pressureInches": "30", "cloudcover": "0", "HeatIndexC": "16", "HeatIndexF": "60", "DewPointC": "-2", "DewPointF": "28", "WindChillC": "16", "WindChillF": "60", "WindGustMiles": "9", "WindGustKmph": "14", "FeelsLikeC": "16", "FeelsLikeF": "60", "uvIndex": "5"}, {"time": "1600", "tempC": "14", "tempF": "58", "windspeedMiles": "7", "windspeedKmph": "11", "winddirDegree": "321", "winddir16Point": "NW", "weatherCode": "113", "weatherIconUrl": [{"value": "http://cdn.worldweatheronline.com/images/wsymbols01_png_64/wsymbol_0001_sunny.png"}], "weatherDesc": [{"value": "Sunny"}], "lang_fr": [{"value": "Ensoleillé"}], "precipMM": "0.0", "precipInches": "0.0", "humidity": "42", "visibility": "10", "visibilityMiles": "6", "pressure": "1019", "pressureInches": "30", "cloudcover": "1", "HeatIndexC": "15", "HeatIndexF": "59", "DewPointC": "0", "DewPointF": "32", "WindChillC": "14", "WindChillF": "58", "WindGustMiles": "8", "WindGustKmph": "13", "FeelsLikeC": "14", "FeelsLikeF": "58", "uvIndex": "4"}, {"time": "1700", "tempC": "13", "tempF": "55", "windspeedMiles": "5", "windspeedKmph": "9", "winddirDegree": "337", "winddir16Point": "NNW", "weatherCode": "116", "weatherIconUrl": [{"value": "http://cdn.worldweatheronline.com/images/wsymbols01_png_64/wsymbol_0002_sunny_intervals.png"}], "weatherDesc": [{"value": "Partly cloudy"}], "lang_fr": [{"value": "Partiellement nuageux"}], "precipMM": "0.0", "precipInches": "0.0", "humidity": "55", "visibility": "10", "visibilityMiles": "6", "pressure": "1019", "pressureInches": "30", "cloudcover": "1", "HeatIndexC": "14", "HeatIndexF": "58", "DewPointC": "3", "DewPointF": "37", "WindChillC": "13", "WindChillF": "55", "WindGustMiles": "8", "WindGustKmph": "12", "FeelsLikeC": "13", "FeelsLikeF": "55", "uvIndex": "4"}, {"time": "1800", "tempC": "12", "tempF": "53", "windspeedMiles": "4", "windspeedKmph": "6", "winddirDegree": "353", "winddir16Point": "N", "weatherCode": "116", "weatherIconUrl": [{"value": "http://cdn.worldweatheronline.com/images/wsymbols01_png_64/wsymbol_0004_black_low_cloud.png"}], "weatherDesc": [{"value": "Partly cloudy"}], "lang_fr": [{"value": "Partiellement nuageux"}], "precipMM": "0.0", "precipInches": "0.0", "humidity": "68", "visibility": "10", "visibilityMiles": "6", "pressure": "1019", "pressureInches": "30", "cloudcover": "2", "HeatIndexC": "14", "HeatIndexF": "57", "DewPointC": "5", "DewPointF": "41", "WindChillC": "12", "WindChillF": "53", "WindGustMiles": "7", "WindGustKmph": "11", "FeelsLikeC": "12", "FeelsLikeF": "53", "uvIndex": "1"}, {"time": "1900", "tempC": "11", "tempF": "51", "windspeedMiles": "3", "windspeedKmph": "5", "winddirDegree": "295", "winddir16Point": "WNW", "weatherCode": "116", "weatherIconUrl": [{"value": "http://cdn.worldweatheronline.com/images/wsymbols01_png_64/wsymbol_0004_black_low_cloud.png"}], "weatherDesc": [{"value": "Partly cloudy"}], "lang_fr": [{"value": "Partiellement nuageux"}], "precipMM": "0.0", "precipInches": "0.0", "humidity": "72", "visibility": "10", "visibilityMiles": "6", "pressure": "1019", "pressureInches": "30", "cloudcover": "3", "HeatIndexC": "12", "HeatIndexF": "53", "DewPointC": "5", "DewPointF": "41", "WindChillC": "11", "WindChillF": "51", "WindGustMiles": "6", "WindGustKmph": "9", "FeelsLikeC": "11", "FeelsLikeF": "51", "uvIndex": "1"}, {"time": "2000", "tempC": "9", "tempF": "49", "windspeedMiles": "3", "windspeedKmph": "4", "winddirDegree": "237", "winddir16Point": "WSW", "weatherCode": "116", "weatherIconUrl": [{"value": "http://cdn.worldweatheronline.com/images/wsymbols01_png_64/wsymbol_0004_black_low_cloud.png"}], "weatherDesc": [{"value": "Partly cloudy"}], "lang_fr": [{"value": "Partiellement nuageux"}], "precipMM": "0.0", "precipInches": "0.0", "humidity": "75", "visibility": "10", "visibilityMiles": "6", "pressure": "1019", "pressureInches": "30", "cloudcover": "4", "HeatIndexC": "10", "HeatIndexF": "50", "DewPointC": "5", "DewPointF": "41", "WindChillC": "9", "WindChillF": "49", "WindGustMiles": "5", "WindGustKmph": "8", "FeelsLikeC": "9", "FeelsLikeF": "49", "uvIndex": "1"}, {"time": "2100", "tempC": "8", "tempF": "47", "windspeedMiles": "2", "windspeedKmph": "3", "winddirDegree": "179", "winddir16Point": "S", "weatherCode": "116", "weatherIconUrl": [{"value": "http://cdn.worldweatheronline.com/images/wsymbols01_png_64/wsymbol_0004_black_low_cloud.png"}], "weatherDesc": [{"value": "Partly cloudy"}], "lang_fr": [{"value": "Partiellement nuageux"}], "precipMM": "0.0", "precipInches": "0.0", "humidity": "79", "visibility": "10", "visibilityMiles": "6", "pressure": "1020", "pressureInches": "30", "cloudcover": "4", "HeatIndexC": "8", "HeatIndexF": "47", "DewPointC": "5", "DewPointF": "40", "WindChillC": "8", "WindChillF": "47", "WindGustMiles": "4", "WindGustKmph": "6", "FeelsLikeC": "8", "FeelsLikeF": "47", "uvIndex": "1"}, {"time": "2200", "tempC": "8", "tempF": "46", "windspeedMiles": "3", "windspeedKmph": "5", "winddirDegree": "182", "winddir16Point": "S", "weatherCode": "116", "weatherIconUrl": [{"value": "http://cdn.worldweatheronline.com/images/wsymbols01_png_64/wsymbol_0004_black_low_cloud.png"}], "weatherDesc": [{"value": "Partly cloudy"}], "lang_fr": [{"value": "Partiellement nuageux"}], "precipMM": "0.0", "precipInches": "0.0", "humidity": "78", "visibility": "10", "visibilityMiles": "6", "pressure": "1020", "pressureInches": "30", "cloudcover": "6", "HeatIndexC": "8", "HeatIndexF": "46", "DewPointC": "4", "DewPointF": "40", "WindChillC": "7", "WindChillF": "45", "WindGustMiles": "6", "WindGustKmph": "10", "FeelsLikeC": "7", "FeelsLikeF": "45", "uvIndex": "1"}, {"time": "2300", "tempC": "7", "tempF": "45", "windspeedMiles": "4", "windspeedKmph": "6", "winddirDegree": "186", "winddir16Point": "S", "weatherCode": "116", "weatherIconUrl": [{"value": "http://cdn.worldweatheronline.com/images/wsymbols01_png_64/wsymbol_0004_black_low_cloud.png"}], "weatherDesc": [{"value": "Partly cloudy"}], "lang_fr": [{"value": "Partiellement nuageux"}], "precipMM": "0.0", "precipInches": "0.0", "humidity": "77", "visibility": "10", "visibilityMiles": "6", "pressure": "1020", "pressureInches": "30", "cloudcover": "8", "HeatIndexC": "7", "HeatIndexF": "45", "DewPointC": "4", "DewPointF": "39", "WindChillC": "6", "WindChillF": "44", "WindGustMiles": "8", "WindGustKmph": "13", "FeelsLikeC": "6", "FeelsLikeF": "44", "uvIndex": "1"}]}]}}