{"data": {"request": [{"type": "City", "query": "Khenifra, Morocco"}], "weather": [{"date": "2021-05-30", "astronomy": [{"sunrise": "06:16 AM", "sunset": "08:32 PM", "moonrise": "12:08 AM", "moonset": "10:09 AM", "moon_phase": "Waning Gibbous", "moon_illumination": "73"}], "maxtempC": "34", "maxtempF": "92", "mintempC": "23", "mintempF": "73", "avgtempC": "29", "avgtempF": "84", "totalSnow_cm": "0.0", "sunHour": "10.5", "uvIndex": "7", "hourly": [{"time": "0", "tempC": "23", "tempF": "73", "windspeedMiles": "5", "windspeedKmph": "9", "winddirDegree": "164", "winddir16Point": "SSE", "weatherCode": "116", "weatherIconUrl": [{"value": "http://cdn.worldweatheronline.com/images/wsymbols01_png_64/wsymbol_0004_black_low_cloud.png"}], "weatherDesc": [{"value": "Partly cloudy"}], "lang_fr": [{"value": "Partiellement nuageux"}], "precipMM": "0.0", "precipInches": "0.0", "humidity": "62", "visibility": "10", "visibilityMiles": "6", "pressure": "1016", "pressureInches": "30", "cloudcover": "22", "HeatIndexC": "25", "HeatIndexF": "77", "DewPointC": "15", "DewPointF": "59", "WindChillC": "23", "WindChillF": "73", "WindGustMiles": "11", "WindGustKmph": "18", "FeelsLikeC": "25", "FeelsLikeF": "77", "uvIndex": "1"}, {"time": "100", "tempC": "23", "tempF": "73", "windspeedMiles": "4", "windspeedKmph": "7", "winddirDegree": "195", "winddir16Point": "SSW", "weatherCode": "116", "weatherIconUrl": [{"value": "http://cdn.worldweatheronline.com/images/wsymbols01_png_64/wsymbol_0004_black_low_cloud.png"}], "weatherDesc": [{"value": "Partly cloudy"}], "lang_fr": [{"value": "Partiellement nuageux"}], "precipMM": "0.0", "precipInches": "0.0", "humidity": "59", "visibility": "10", "visibilityMiles": "6", "pressure": "1015", "pressureInches": "30", "cloudcover": "26", "HeatIndexC": "25", "HeatIndexF": "77", "DewPointC": "14", "DewPointF": "58", "WindChillC": "23", "WindChillF": "73", "WindGustMiles": "9", "WindGustKmph": "14", "FeelsLikeC": "25", "FeelsLikeF": "77", "uvIndex": "1"}, {"time": "200", "tempC": "23", "tempF": "73", "windspeedMiles": "3", "windspeedKmph": "5", "winddirDegree": "226", "winddir16Point": "SW", "weatherCode": "116", "weatherIconUrl": [{"value": "http://cdn.worldweatheronline.com/images/wsymbols01_png_64/wsymbol_0004_black_low_cloud.png"}], "weatherDesc": [{"value": "Partly cloudy"}], "lang_fr": [{"value": "Partiellement nuageux"}], "precipMM": "0.0", "precipInches": "0.0", "humidity": "57", "visibility": "10", "visibilityMiles": "6", "pressure": "1015", "pressureInches": "30", "cloudcover": "30", "HeatIndexC": "25", "HeatIndexF": "77", "DewPointC": "14", "DewPointF": "57", "WindChillC": "23", "WindChillF": "73", "WindGustMiles": "6", "WindGustKmph": "10", "FeelsLikeC": "25", "FeelsLikeF": "77", "uvIndex": "1"}, {"time": "300", "tempC": "23", "tempF": "73", "windspeedMiles": "2", "windspeedKmph": "3", "winddirDegree": "257", "winddir16Point": "WSW", "weatherCode": "116", "weatherIconUrl": [{"value": "http://cdn.worldweatheronline.com/images/wsymbols01_png_64/wsymbol_0004_black_low_cloud.png"}], "weatherDesc": [{"value": "Partly cloudy"}], "lang_fr": [{"value": "Partiellement nuageux"}], "precipMM": "0.0", "precipInches": "0.0", "humidity": "54", "visibility": "10", "visibilityMiles": "6", "pressure": "1014", "pressureInches": "30", "cloudcover": "34", "HeatIndexC": "25", "HeatIndexF": "77", "DewPointC": "13", "DewPointF": "56", "WindChillC": "23", "WindChillF": "73", "WindGustMiles": "4", "WindGustKmph": "6", "FeelsLikeC": "25", "FeelsLikeF": "77", "uvIndex": "1"}, {"time": "400", "tempC": "23", "tempF": "74", "windspeedMiles": "4", "windspeedKmph": "6", "winddirDegree": "200", "winddir16Point": "SSW", "weatherCode": "116", "weatherIconUrl": [{"value": "http://cdn.worldweatheronline.com/images/wsymbols01_png_64/wsymbol_0004_black_low_cloud.png"}], "weatherDesc": [{"value": "Partly cloudy"}], "lang_fr": [{"value": "Partiellement nuageux"}], "precipMM": "0.0", "precipInches": "0.0", "humidity": "52", "visibility": "10", "visibilityMiles": "6", "pressure": "1014", "pressureInches": "30", "cloudcover": "38", "HeatIndexC": "25", "HeatIndexF": "77", "DewPointC": "13", "DewPointF": "55", "WindChillC": "23", "WindChillF": "74", "WindGustMiles": "8", "WindGustKmph": "13", "FeelsLikeC": "25", "FeelsLikeF": "77", "uvIndex": "1"}, {"time": "500", "tempC": "24", "tempF": "74", "windspeedMiles": "6", "windspeedKmph": "10", "winddirDegree": "143", "winddir16Point": "SE", "weatherCode": "116", "weatherIconUrl": [{"value": "http://cdn.worldweatheronline.com/images/wsymbols01_png_64/wsymbol_0004_black_low_cloud.png"}], "weatherDesc": [{"value": "Partly cloudy"}], "lang_fr": [{"value": "Partiellement nuageux"}], "precipMM": "0.0", "precipInches": "0.0", "humidity": "50", "visibility": "10", "visibilityMiles": "6", "pressure": "1014", "pressureInches": "30", "cloudcover": "43", "HeatIndexC": "25", "HeatIndexF": "77", "DewPointC": "12", "DewPointF": "54", "WindChillC": "24", "WindChillF": "74", "WindGustMiles": "13", "WindGustKmph": "21", "FeelsLikeC": "25", "FeelsLikeF": "77", "uvIndex": "1"}, {"time": "600", "tempC": "24", "tempF": "75", "windspeedMiles": "8", "windspeedKmph": "13", "winddirDegree": "86", "winddir16Point": "E", "weatherCode": "116", "weatherIconUrl": [{"value": "http://cdn.worldweatheronline.com/images/wsymbols01_png_64/wsymbol_0002_sunny_intervals.png"}], "weatherDesc": [{"value": "Partly cloudy"}], "lang_fr": [{"value": "Partiellement nuageux"}], "precipMM": "0.0", "precipInches": "0.0", "humidity": "48", "visibility": "10", "visibilityMiles": "6", "pressure": "1013", "pressureInches": "30", "cloudcover": "48", "HeatIndexC": "25", "HeatIndexF": "77", "DewPointC": "12", "DewPointF": "54", "WindChillC": "24", "WindChillF": "75", "WindGustMiles": "17", "WindGustKmph": "28", "FeelsLikeC": "25", "FeelsLikeF": "77", "uvIndex": "6"}, {"time": "700", "tempC": "26", "tempF": "78", "windspeedMiles": "8", "windspeedKmph": "12", "winddirDegree": "88", "winddir16Point": "E", "weatherCode": "116", "weatherIconUrl": [{"value": "http://cdn.worldweatheronline.com/images/wsymbols01_png_64/wsymbol_0002_sunny_intervals.png"}], "weatherDesc": [{"value": "Partly cloudy"}], "lang_fr": [{"value": "Partiellement nuageux"}], "precipMM": "0.0", "precipInches": "0.0", "humidity": "46", "visibility": "10", "visibilityMiles": "6", "pressure": "1013", "pressureInches": "30", "cloudcover": "39", "HeatIndexC": "26", "HeatIndexF": "80", "DewPointC": "13", "DewPointF": "55", "WindChillC": "26", "WindChillF": "78", "WindGustMiles": "16", "WindGustKmph": "25", "FeelsLikeC": "26", "FeelsLikeF": "80", "uvIndex": "7"}, {"time": "800", "tempC": "27", "tempF": "81", "windspeedMiles": "7", "windspeedKmph": "12", "winddirDegree": "89", "winddir16Point": "E", "weatherCode": "116", "weatherIconUrl": [{"value": "http://cdn.worldweatheronline.com/images/wsymbols01_png_64/wsymbol_0002_sunny_intervals.png"}], "weatherDesc": [{"value": "Partly cloudy"}], "lang_fr": [{"value": "Partiellement nuageux"}], "precipMM": "0.0", "precipInches": "0.0", "humidity": "43", "visibility": "10", "visibilityMiles": "6", "pressure": "1013", "pressureInches": "30", "cloudcover": "31", "HeatIndexC": "28", "HeatIndexF": "82", "DewPointC": "14", "DewPointF": "57", "WindChillC": "27", "WindChillF": "81", "WindGustMiles": "14", "WindGustKmph": "22", "FeelsLikeC": "28", "FeelsLikeF": "82", "uvIndex": "7"}, {"time": "900", "tempC": "29", "tempF": "85", "windspeedMiles": "7", "windspeedKmph": "11", "winddirDegree": "91", "winddir16Point": "E", "weatherCode": "116", "weatherIconUrl": [{"value": "http://cdn.worldweatheronline.com/images/wsymbols01_png_64/wsymbol_0002_sunny_intervals.png"}], "weatherDesc": [{"value": "Partly cloudy"}], "lang_fr": [{"value": "Partiellement nuageux"}], "precipMM": "0.0", "precipInches": "0.0", "humidity": "41", "visibility": "10", "visibilityMiles": "6", "pressure": "1013", "pressureInches": "30", "cloudcover": "22", "HeatIndexC": "29", "HeatIndexF": "85", "DewPointC": "15", "DewPointF": "58", "WindChillC": "29", "WindChillF": "85", "WindGustMiles": "12", "WindGustKmph": "19", "FeelsLikeC": "29", "FeelsLikeF": "85", "uvIndex": "7"}, {"time": "1000", "tempC": "29", "tempF": "84", "windspeedMiles": "8", "windspeedKmph": "13", "winddirDegree": "177", "winddir16Point": "S", "weatherCode": "116", "weatherIconUrl": [{"value": "http://cdn.worldweatheronline.com/images/wsymbols01_png_64/wsymbol_0002_sunny_intervals.png"}], "weatherDesc": [{"value": "Partly cloudy"}], "lang_fr": [{"value": "Partiellement nuageux"}], "precipMM": "0.0", "precipInches": "0.0", "humidity": "42", "visibility": "10", "visibilityMiles": "6", "pressure": "1013", "pressureInches": "30", "cloudcover": "31", "HeatIndexC": "29", "HeatIndexF": "85", "DewPointC": "15", "DewPointF": "59", "WindChillC": "29", "WindChillF": "84", "WindGustMiles": "15", "WindGustKmph": "24", "FeelsLikeC": "29", "FeelsLikeF": "85", "uvIndex": "7"}, {"time": "1100", "tempC": "29", "tempF": "84", "windspeedMiles": "10", "windspeedKmph": "16", "winddirDegree": "263", "winddir16Point": "W", "weatherCode": "116", "weatherIconUrl": [{"value": "http://cdn.worldweatheronline.com/images/wsymbols01_png_64/wsymbol_0002_sunny_intervals.png"}], "weatherDesc": [{"value": "Partly cloudy"}], "lang_fr": [{"value": "Partiellement nuageux"}], "precipMM": "0.0", "precipInches": "0.0", "humidity": "44", "visibility": "10", "visibilityMiles": "6", "pressure": "1014", "pressureInches": "30", "cloudcover": "40", "HeatIndexC": "29", "HeatIndexF": "85", "DewPointC": "15", "DewPointF": "60", "WindChillC": "29", "WindChillF": "84", "WindGustMiles": "18", "WindGustKmph": "30", "FeelsLikeC": "29", "FeelsLikeF": "85", "uvIndex": "7"}, {"time": "1200", "tempC": "29", "tempF": "84", "windspeedMiles": "11", "windspeedKmph": "18", "winddirDegree": "349", "winddir16Point": "NNW", "weatherCode": "116", "weatherIconUrl": [{"value": "http://cdn.worldweatheronline.com/images/wsymbols01_png_64/wsymbol_0002_sunny_intervals.png"}], "weatherDesc": [{"value": "Partly cloudy"}], "lang_fr": [{"value": "Partiellement nuageux"}], "precipMM": "0.0", "precipInches": "0.0", "humidity": "45", "visibility": "10", "visibilityMiles": "6", "pressure": "1014", "pressureInches": "30", "cloudcover": "48", "HeatIndexC": "29", "HeatIndexF": "85", "DewPointC": "16", "DewPointF": "61", "WindChillC": "29", "WindChillF": "84", "WindGustMiles": "22", "WindGustKmph": "35", "FeelsLikeC": "29", "FeelsLikeF": "85", "uvIndex": "7"}, {"time": "1300", "tempC": "30", "tempF": "87", "windspeedMiles": "13", "windspeedKmph": "21", "winddirDegree": "245", "winddir16Point": "WSW", "weatherCode": "116", "weatherIconUrl": [{"value": "http://cdn.worldweatheronline.com/images/wsymbols01_png_64/wsymbol_0002_sunny_intervals.png"}], "weatherDesc": [{"value": "Partly cloudy"}], "lang_fr": [{"value": "Partiellement nuageux"}], "precipMM": "0.0", "precipInches": "0.0", "humidity": "40", "visibility": "10", "visibilityMiles": "6", "pressure": "1013", "pressureInches": "30", "cloudcover": "48", "HeatIndexC": "31", "HeatIndexF": "87", "DewPointC": "15", "DewPointF": "59", "WindChillC": "30", "WindChillF": "87", "WindGustMiles": "24", "WindGustKmph": "39", "FeelsLikeC": "31", "FeelsLikeF": "87", "uvIndex": "8"}, {"time": "1400", "tempC": "32", "tempF": "90", "windspeedMiles": "14", "windspeedKmph": "23", "winddirDegree": "141", "winddir16Point": "SE", "weatherCode": "116", "weatherIconUrl": [{"value": "http://cdn.worldweatheronline.com/images/wsymbols01_png_64/wsymbol_0002_sunny_intervals.png"}], "weatherDesc": [{"value": "Partly cloudy"}], "lang_fr": [{"value": "Partiellement nuageux"}], "precipMM": "0.0", "precipInches": "0.0", "humidity": "35", "visibility": "10", "visibilityMiles": "6", "pressure": "1012", "pressureInches": "30", "cloudcover": "47", "HeatIndexC": "32", "HeatIndexF": "89", "DewPointC": "15", "DewPointF": "58", "WindChillC": "32", "WindChillF": "90", "WindGustMiles": "27", "WindGustKmph": "43", "FeelsLikeC": "32", "FeelsLikeF": "89", "uvIndex": "8"}, {"time": "1500", "tempC": "34", "tempF": "92", "windspeedMiles": "16", "windspeedKmph": "26", "winddirDegree": "37", "winddir16Point": "NE", "weatherCode": "116", "weatherIconUrl": [{"value": "http://cdn.worldweatheronline.com/images/wsymbols01_png_64/wsymbol_0002_sunny_intervals.png"}], "weatherDesc": [{"value": "Partly cloudy"}], "lang_fr": [{"value": "Partiellement nuageux"}], "precipMM": "0.0", "precipInches": "0.0", "humidity": "30", "visibility": "10", "visibilityMiles": "6", "pressure": "1011", "pressureInches": "30", "cloudcover": "47", "HeatIndexC": "33", "HeatIndexF": "92", "DewPointC": "14", "DewPointF": "57", "WindChillC": "34", "WindChillF": "92", "WindGustMiles": "29", "WindGustKmph": "47", "FeelsLikeC": "33", "FeelsLikeF": "92", "uvIndex": "8"}, {"time": "1600", "tempC": "32", "tempF": "90", "windspeedMiles": "17", "windspeedKmph": "27", "winddirDegree": "49", "winddir16Point": "NE", "weatherCode": "116", "weatherIconUrl": [{"value": "http://cdn.worldweatheronline.com/images/wsymbols01_png_64/wsymbol_0002_sunny_intervals.png"}], "weatherDesc": [{"value": "Partly cloudy"}], "lang_fr": [{"value": "Partiellement nuageux"}], "precipMM": "0.0", "precipInches": "0.0", "humidity": "29", "visibility": "10", "visibilityMiles": "6", "pressure": "1011", "pressureInches": "30", "cloudcover": "59", "HeatIndexC": "33", "HeatIndexF": "92", "DewPointC": "13", "DewPointF": "55", "WindChillC": "32", "WindChillF": "90", "WindGustMiles": "31", "WindGustKmph": "50", "FeelsLikeC": "33", "FeelsLikeF": "92", "uvIndex": "8"}, {"time": "1700", "tempC": "31", "tempF": "88", "windspeedMiles": "18", "windspeedKmph": "29", "winddirDegree": "61", "winddir16Point": "ENE", "weatherCode": "176", "weatherIconUrl": [{"value": "http://cdn.worldweatheronline.com/images/wsymbols01_png_64/wsymbol_0009_light_rain_showers.png"}], "weatherDesc": [{"value": "Patchy rain possible"}], "lang_fr": [{"value": "Pluie éparse à proximité"}], "precipMM": "0.0", "precipInches": "0.0", "humidity": "27", "visibility": "10", "visibilityMiles": "6", "pressure": "1011", "pressureInches": "30", "cloudcover": "71", "HeatIndexC": "33", "HeatIndexF": "92", "DewPointC": "12", "DewPointF": "54", "WindChillC": "31", "WindChillF": "88", "WindGustMiles": "33", "WindGustKmph": "53", "FeelsLikeC": "33", "FeelsLikeF": "92", "uvIndex": "7"}, {"time": "1800", "tempC": "30", "tempF": "85", "windspeedMiles": "19", "windspeedKmph": "30", "winddirDegree": "73", "winddir16Point": "ENE", "weatherCode": "176", "weatherIconUrl": [{"value": "http://cdn.worldweatheronline.com/images/wsymbols01_png_64/wsymbol_0025_light_rain_showers_night.png"}], "weatherDesc": [{"value": "Patchy rain possible"}], "lang_fr": [{"value": "Pluie éparse à proximité"}], "precipMM": "0.0", "precipInches": "0.0", "humidity": "26", "visibility": "10", "visibilityMiles": "6", "pressure": "1010", "pressureInches": "30", "cloudcover": "83", "HeatIndexC": "34", "HeatIndexF": "92", "DewPointC": "12", "DewPointF": "53", "WindChillC": "30", "WindChillF": "85", "WindGustMiles": "35", "WindGustKmph": "56", "FeelsLikeC": "34", "FeelsLikeF": "92", "uvIndex": "1"}, {"time": "1900", "tempC": "29", "tempF": "85", "windspeedMiles": "18", "windspeedKmph": "29", "winddirDegree": "80", "winddir16Point": "E", "weatherCode": "176", "weatherIconUrl": [{"value": "http://cdn.worldweatheronline.com/images/wsymbols01_png_64/wsymbol_0025_light_rain_showers_night.png"}], "weatherDesc": [{"value": "Patchy rain possible"}], "lang_fr": [{"value": "Pluie éparse à proximité"}], "precipMM": "0.0", "precipInches": "0.0", "humidity": "30", "visibility": "10", "visibilityMiles": "6", "pressure": "1011", "pressureInches": "30", "cloudcover": "81", "HeatIndexC": "32", "HeatIndexF": "89", "DewPointC": "12", "DewPointF": "54", "WindChillC": "29", "WindChillF": "85", "WindGustMiles": "34", "WindGustKmph": "55", "FeelsLikeC": "32", "FeelsLikeF": "89", "uvIndex": "1"}, {"time": "2000", "tempC": "29", "tempF": "85", "windspeedMiles": "17", "windspeedKmph": "28", "winddirDegree": "88", "winddir16Point": "E", "weatherCode": "176", "weatherIconUrl": [{"value": "http://cdn.worldweatheronline.com/images/wsymbols01_png_64/wsymbol_0025_light_rain_showers_night.png"}], "weatherDesc": [{"value": "Patchy rain possible"}], "lang_fr": [{"value": "Pluie éparse à proximité"}], "precipMM": "0.0", "precipInches": "0.0", "humidity": "34", "visibility": "10", "visibilityMiles": "6", "pressure": "1011", "pressureInches": "30", "cloudcover": "78", "HeatIndexC": "30", "HeatIndexF": "87", "DewPointC": "13", "DewPointF": "55", "WindChillC": "29", "WindChillF": "85", "WindGustMiles": "33", "WindGustKmph": "53", "FeelsLikeC": "30", "FeelsLikeF": "87", "uvIndex": "1"}, {"time": "2100", "tempC": "29", "tempF": "84", "windspeedMiles": "17", "windspeedKmph": "27", "winddirDegree": "95", "winddir16Point": "E", "weatherCode": "176", "weatherIconUrl": [{"value": "http://cdn.worldweatheronline.com/images/wsymbols01_png_64/wsymbol_0025_light_rain_showers_night.png"}], "weatherDesc": [{"value": "Patchy rain possible"}], "lang_fr": [{"value": "Pluie éparse à proximité"}], "precipMM": "0.0", "precipInches": "0.0", "humidity": "38", "visibility": "10", "visibilityMiles": "6", "pressure": "1011", "pressureInches": "30", "cloudcover": "76", "HeatIndexC": "29", "HeatIndexF": "84", "DewPointC": "13", "DewPointF": "56", "WindChillC": "29", "WindChillF": "84", "WindGustMiles": "32", "WindGustKmph": "52", "FeelsLikeC": "29", "FeelsLikeF": "84", "uvIndex": "1"}, {"time": "2200", "tempC": "28", "tempF": "83", "windspeedMiles": "15", "windspeedKmph": "24", "winddirDegree": "95", "winddir16Point": "E", "weatherCode": "176", "weatherIconUrl": [{"value": "http://cdn.worldweatheronline.com/images/wsymbols01_png_64/wsymbol_0025_light_rain_showers_night.png"}], "weatherDesc": [{"value": "Patchy rain possible"}], "lang_fr": [{"value": "Pluie éparse à proximité"}], "precipMM": "0.0", "precipInches": "0.0", "humidity": "40", "visibility": "10", "visibilityMiles": "6", "pressure": "1011", "pressureInches": "30", "cloudcover": "54", "HeatIndexC": "28", "HeatIndexF": "83", "DewPointC": "13", "DewPointF": "56", "WindChillC": "28", "WindChillF": "83", "WindGustMiles": "30", "WindGustKmph": "48", "FeelsLikeC": "28", "FeelsLikeF": "83", "uvIndex": "1"}, {"time": "2300", "tempC": "27", "tempF": "81", "windspeedMiles": "13", "windspeedKmph": "22", "winddirDegree": "94", "winddir16Point": "E", "weatherCode": "116", "weatherIconUrl": [{"value": "http://cdn.worldweatheronline.com/images/wsymbols01_png_64/wsymbol_0004_black_low_cloud.png"}], "weatherDesc": [{"value": "Partly cloudy"}], "lang_fr": [{"value": "Partiellement nuageux"}], "precipMM": "0.0", "precipInches": "0.0", "humidity": "42", "visibility": "10", "visibilityMiles": "6", "pressure": "1011", "pressureInches": "30", "cloudcover": "31", "HeatIndexC": "28", "HeatIndexF": "82", "DewPointC": "13", "DewPointF": "56", "WindChillC": "27", "WindChillF": "81", "WindGustMiles": "27", "WindGustKmph": "44", "FeelsLikeC": "28", "FeelsLikeF": "82", "uvIndex": "1"}]}]}}