{"data": {"request": [{"type": "City", "query": "Guelmim, Morocco"}], "weather": [{"date": "2021-09-11", "astronomy": [{"sunrise": "07:23 AM", "sunset": "07:50 PM", "moonrise": "11:54 AM", "moonset": "11:01 PM", "moon_phase": "Waxing Crescent", "moon_illumination": "31"}], "maxtempC": "42", "maxtempF": "107", "mintempC": "21", "mintempF": "70", "avgtempC": "34", "avgtempF": "92", "totalSnow_cm": "0.0", "sunHour": "11.6", "uvIndex": "8", "hourly": [{"time": "0", "tempC": "22", "tempF": "71", "windspeedMiles": "2", "windspeedKmph": "4", "winddirDegree": "302", "winddir16Point": "WNW", "weatherCode": "116", "weatherIconUrl": [{"value": "http://cdn.worldweatheronline.com/images/wsymbols01_png_64/wsymbol_0004_black_low_cloud.png"}], "weatherDesc": [{"value": "Partly cloudy"}], "lang_fr": [{"value": "Partiellement nuageux"}], "precipMM": "0.0", "precipInches": "0.0", "humidity": "54", "visibility": "10", "visibilityMiles": "6", "pressure": "1017", "pressureInches": "30", "cloudcover": "1", "HeatIndexC": "24", "HeatIndexF": "76", "DewPointC": "12", "DewPointF": "53", "WindChillC": "22", "WindChillF": "71", "WindGustMiles": "5", "WindGustKmph": "8", "FeelsLikeC": "22", "FeelsLikeF": "71", "uvIndex": "1"}, {"time": "100", "tempC": "22", "tempF": "71", "windspeedMiles": "2", "windspeedKmph": "4", "winddirDegree": "313", "winddir16Point": "NW", "weatherCode": "116", "weatherIconUrl": [{"value": "http://cdn.worldweatheronline.com/images/wsymbols01_png_64/wsymbol_0004_black_low_cloud.png"}], "weatherDesc": [{"value": "Partly cloudy"}], "lang_fr": [{"value": "Partiellement nuageux"}], "precipMM": "0.0", "precipInches": "0.0", "humidity": "51", "visibility": "10", "visibilityMiles": "6", "pressure": "1016", "pressureInches": "30", "cloudcover": "1", "HeatIndexC": "24", "HeatIndexF": "76", "DewPointC": "11", "DewPointF": "52", "WindChillC": "22", "WindChillF": "71", "WindGustMiles": "5", "WindGustKmph": "8", "FeelsLikeC": "22", "FeelsLikeF": "71", "uvIndex": "1"}, {"time": "200", "tempC": "22", "tempF": "71", "windspeedMiles": "2", "windspeedKmph": "4", "winddirDegree": "323", "winddir16Point": "NW", "weatherCode": "113", "weatherIconUrl": [{"value": "http://cdn.worldweatheronline.com/images/wsymbols01_png_64/wsymbol_0008_clear_sky_night.png"}], "weatherDesc": [{"value": "Clear"}], "lang_fr": [{"value": "Clair"}], "precipMM": "0.0", "precipInches": "0.0", "humidity": "48", "visibility": "10", "visibilityMiles": "6", "pressure": "1016", "pressureInches": "30", "cloudcover": "0", "HeatIndexC": "24", "HeatIndexF": "76", "DewPointC": "10", "DewPointF": "50", "WindChillC": "22", "WindChillF": "71", "WindGustMiles": "5", "WindGustKmph": "8", "FeelsLikeC": "22", "FeelsLikeF": "71", "uvIndex": "1"}, {"time": "300", "tempC": "22", "tempF": "71", "windspeedMiles": "2", "windspeedKmph": "4", "winddirDegree": "333", "winddir16Point": "NNW", "weatherCode": "113", "weatherIconUrl": [{"value": "http://cdn.worldweatheronline.com/images/wsymbols01_png_64/wsymbol_0008_clear_sky_night.png"}], "weatherDesc": [{"value": "Clear"}], "lang_fr": [{"value": "Clair"}], "precipMM": "0.0", "precipInches": "0.0", "humidity": "45", "visibility": "10", "visibilityMiles": "6", "pressure": "1015", "pressureInches": "30", "cloudcover": "0", "HeatIndexC": "24", "HeatIndexF": "75", "DewPointC": "9", "DewPointF": "48", "WindChillC": "22", "WindChillF": "71", "WindGustMiles": "5", "WindGustKmph": "8", "FeelsLikeC": "22", "FeelsLikeF": "71", "uvIndex": "1"}, {"time": "400", "tempC": "21", "tempF": "71", "windspeedMiles": "2", "windspeedKmph": "4", "winddirDegree": "319", "winddir16Point": "NW", "weatherCode": "113", "weatherIconUrl": [{"value": "http://cdn.worldweatheronline.com/images/wsymbols01_png_64/wsymbol_0008_clear_sky_night.png"}], "weatherDesc": [{"value": "Clear"}], "lang_fr": [{"value": "Clair"}], "precipMM": "0.0", "precipInches": "0.0", "humidity": "43", "visibility": "10", "visibilityMiles": "6", "pressure": "1015", "pressureInches": "30", "cloudcover": "1", "HeatIndexC": "23", "HeatIndexF": "74", "DewPointC": "8", "DewPointF": "47", "WindChillC": "21", "WindChillF": "71", "WindGustMiles": "5", "WindGustKmph": "8", "FeelsLikeC": "21", "FeelsLikeF": "71", "uvIndex": "1"}, {"time": "500", "tempC": "21", "tempF": "70", "windspeedMiles": "2", "windspeedKmph": "4", "winddirDegree": "305", "winddir16Point": "NW", "weatherCode": "116", "weatherIconUrl": [{"value": "http://cdn.worldweatheronline.com/images/wsymbols01_png_64/wsymbol_0004_black_low_cloud.png"}], "weatherDesc": [{"value": "Partly cloudy"}], "lang_fr": [{"value": "Partiellement nuageux"}], "precipMM": "0.0", "precipInches": "0.0", "humidity": "41", "visibility": "10", "visibilityMiles": "6", "pressure": "1015", "pressureInches": "30", "cloudcover": "2", "HeatIndexC": "22", "HeatIndexF": "72", "DewPointC": "8", "DewPointF": "46", "WindChillC": "21", "WindChillF": "70", "WindGustMiles": "5", "WindGustKmph": "8", "FeelsLikeC": "21", "FeelsLikeF": "70", "uvIndex": "1"}, {"time": "600", "tempC": "21", "tempF": "70", "windspeedMiles": "2", "windspeedKmph": "4", "winddirDegree": "291", "winddir16Point": "WNW", "weatherCode": "116", "weatherIconUrl": [{"value": "http://cdn.worldweatheronline.com/images/wsymbols01_png_64/wsymbol_0002_sunny_intervals.png"}], "weatherDesc": [{"value": "Partly cloudy"}], "lang_fr": [{"value": "Partiellement nuageux"}], "precipMM": "0.0", "precipInches": "0.0", "humidity": "40", "visibility": "10", "visibilityMiles": "6", "pressure": "1015", "pressureInches": "30", "cloudcover": "4", "HeatIndexC": "21", "HeatIndexF": "70", "DewPointC": "7", "DewPointF": "44", "WindChillC": "21", "WindChillF": "70", "WindGustMiles": "5", "WindGustKmph": "8", "FeelsLikeC": "21", "FeelsLikeF": "70", "uvIndex": "6"}, {"time": "700", "tempC": "24", "tempF": "76", "windspeedMiles": "3", "windspeedKmph": "4", "winddirDegree": "287", "winddir16Point": "WNW", "weatherCode": "116", "weatherIconUrl": [{"value": "http://cdn.worldweatheronline.com/images/wsymbols01_png_64/wsymbol_0002_sunny_intervals.png"}], "weatherDesc": [{"value": "Partly cloudy"}], "lang_fr": [{"value": "Partiellement nuageux"}], "precipMM": "0.0", "precipInches": "0.0", "humidity": "33", "visibility": "10", "visibilityMiles": "6", "pressure": "1015", "pressureInches": "30", "cloudcover": "7", "HeatIndexC": "24", "HeatIndexF": "74", "DewPointC": "6", "DewPointF": "44", "WindChillC": "24", "WindChillF": "76", "WindGustMiles": "5", "WindGustKmph": "7", "FeelsLikeC": "24", "FeelsLikeF": "74", "uvIndex": "6"}, {"time": "800", "tempC": "28", "tempF": "82", "windspeedMiles": "3", "windspeedKmph": "4", "winddirDegree": "283", "winddir16Point": "WNW", "weatherCode": "116", "weatherIconUrl": [{"value": "http://cdn.worldweatheronline.com/images/wsymbols01_png_64/wsymbol_0002_sunny_intervals.png"}], "weatherDesc": [{"value": "Partly cloudy"}], "lang_fr": [{"value": "Partiellement nuageux"}], "precipMM": "0.0", "precipInches": "0.0", "humidity": "27", "visibility": "10", "visibilityMiles": "6", "pressure": "1015", "pressureInches": "30", "cloudcover": "11", "HeatIndexC": "26", "HeatIndexF": "79", "DewPointC": "6", "DewPointF": "43", "WindChillC": "28", "WindChillF": "82", "WindGustMiles": "4", "WindGustKmph": "6", "FeelsLikeC": "26", "FeelsLikeF": "79", "uvIndex": "7"}, {"time": "900", "tempC": "31", "tempF": "87", "windspeedMiles": "3", "windspeedKmph": "4", "winddirDegree": "279", "winddir16Point": "W", "weatherCode": "116", "weatherIconUrl": [{"value": "http://cdn.worldweatheronline.com/images/wsymbols01_png_64/wsymbol_0002_sunny_intervals.png"}], "weatherDesc": [{"value": "Partly cloudy"}], "lang_fr": [{"value": "Partiellement nuageux"}], "precipMM": "0.0", "precipInches": "0.0", "humidity": "20", "visibility": "10", "visibilityMiles": "6", "pressure": "1015", "pressureInches": "30", "cloudcover": "15", "HeatIndexC": "29", "HeatIndexF": "83", "DewPointC": "6", "DewPointF": "42", "WindChillC": "31", "WindChillF": "87", "WindGustMiles": "3", "WindGustKmph": "5", "FeelsLikeC": "29", "FeelsLikeF": "83", "uvIndex": "8"}, {"time": "1000", "tempC": "34", "tempF": "93", "windspeedMiles": "5", "windspeedKmph": "8", "winddirDegree": "281", "winddir16Point": "WNW", "weatherCode": "116", "weatherIconUrl": [{"value": "http://cdn.worldweatheronline.com/images/wsymbols01_png_64/wsymbol_0002_sunny_intervals.png"}], "weatherDesc": [{"value": "Partly cloudy"}], "lang_fr": [{"value": "Partiellement nuageux"}], "precipMM": "0.0", "precipInches": "0.0", "humidity": "19", "visibility": "10", "visibilityMiles": "6", "pressure": "1015", "pressureInches": "30", "cloudcover": "12", "HeatIndexC": "33", "HeatIndexF": "91", "DewPointC": "7", "DewPointF": "44", "WindChillC": "34", "WindChillF": "93", "WindGustMiles": "6", "WindGustKmph": "10", "FeelsLikeC": "33", "FeelsLikeF": "91", "uvIndex": "8"}, {"time": "1100", "tempC": "37", "tempF": "99", "windspeedMiles": "7", "windspeedKmph": "12", "winddirDegree": "283", "winddir16Point": "WNW", "weatherCode": "116", "weatherIconUrl": [{"value": "http://cdn.worldweatheronline.com/images/wsymbols01_png_64/wsymbol_0002_sunny_intervals.png"}], "weatherDesc": [{"value": "Partly cloudy"}], "lang_fr": [{"value": "Partiellement nuageux"}], "precipMM": "0.0", "precipInches": "0.0", "humidity": "17", "visibility": "10", "visibilityMiles": "6", "pressure": "1015", "pressureInches": "30", "cloudcover": "9", "HeatIndexC": "37", "HeatIndexF": "98", "DewPointC": "8", "DewPointF": "46", "WindChillC": "37", "WindChillF": "99", "WindGustMiles": "9", "WindGustKmph": "14", "FeelsLikeC": "37", "FeelsLikeF": "98", "uvIndex": "9"}, {"time": "1200", "tempC": "41", "tempF": "105", "windspeedMiles": "10", "windspeedKmph": "16", "winddirDegree": "286", "winddir16Point": "WNW", "weatherCode": "116", "weatherIconUrl": [{"value": "http://cdn.worldweatheronline.com/images/wsymbols01_png_64/wsymbol_0002_sunny_intervals.png"}], "weatherDesc": [{"value": "Partly cloudy"}], "lang_fr": [{"value": "Partiellement nuageux"}], "precipMM": "0.0", "precipInches": "0.0", "humidity": "15", "visibility": "10", "visibilityMiles": "6", "pressure": "1015", "pressureInches": "30", "cloudcover": "6", "HeatIndexC": "41", "HeatIndexF": "105", "DewPointC": "9", "DewPointF": "47", "WindChillC": "41", "WindChillF": "105", "WindGustMiles": "11", "WindGustKmph": "18", "FeelsLikeC": "41", "FeelsLikeF": "105", "uvIndex": "10"}, {"time": "1300", "tempC": "41", "tempF": "106", "windspeedMiles": "11", "windspeedKmph": "18", "winddirDegree": "293", "winddir16Point": "WNW", "weatherCode": "116", "weatherIconUrl": [{"value": "http://cdn.worldweatheronline.com/images/wsymbols01_png_64/wsymbol_0002_sunny_intervals.png"}], "weatherDesc": [{"value": "Partly cloudy"}], "lang_fr": [{"value": "Partiellement nuageux"}], "precipMM": "0.0", "precipInches": "0.0", "humidity": "14", "visibility": "10", "visibilityMiles": "6", "pressure": "1014", "pressureInches": "30", "cloudcover": "5", "HeatIndexC": "41", "HeatIndexF": "106", "DewPointC": "8", "DewPointF": "46", "WindChillC": "41", "WindChillF": "106", "WindGustMiles": "13", "WindGustKmph": "21", "FeelsLikeC": "41", "FeelsLikeF": "106", "uvIndex": "10"}, {"time": "1400", "tempC": "41", "tempF": "106", "windspeedMiles": "13", "windspeedKmph": "21", "winddirDegree": "301", "winddir16Point": "WNW", "weatherCode": "116", "weatherIconUrl": [{"value": "http://cdn.worldweatheronline.com/images/wsymbols01_png_64/wsymbol_0002_sunny_intervals.png"}], "weatherDesc": [{"value": "Partly cloudy"}], "lang_fr": [{"value": "Partiellement nuageux"}], "precipMM": "0.0", "precipInches": "0.0", "humidity": "13", "visibility": "10", "visibilityMiles": "6", "pressure": "1014", "pressureInches": "30", "cloudcover": "4", "HeatIndexC": "42", "HeatIndexF": "107", "DewPointC": "7", "DewPointF": "45", "WindChillC": "41", "WindChillF": "106", "WindGustMiles": "15", "WindGustKmph": "24", "FeelsLikeC": "42", "FeelsLikeF": "107", "uvIndex": "10"}, {"time": "1500", "tempC": "42", "tempF": "107", "windspeedMiles": "15", "windspeedKmph": "23", "winddirDegree": "308", "winddir16Point": "NW", "weatherCode": "116", "weatherIconUrl": [{"value": "http://cdn.worldweatheronline.com/images/wsymbols01_png_64/wsymbol_0002_sunny_intervals.png"}], "weatherDesc": [{"value": "Partly cloudy"}], "lang_fr": [{"value": "Partiellement nuageux"}], "precipMM": "0.0", "precipInches": "0.0", "humidity": "12", "visibility": "10", "visibilityMiles": "6", "pressure": "1013", "pressureInches": "30", "cloudcover": "3", "HeatIndexC": "42", "HeatIndexF": "108", "DewPointC": "6", "DewPointF": "43", "WindChillC": "42", "WindChillF": "107", "WindGustMiles": "17", "WindGustKmph": "27", "FeelsLikeC": "42", "FeelsLikeF": "108", "uvIndex": "10"}, {"time": "1600", "tempC": "39", "tempF": "102", "windspeedMiles": "13", "windspeedKmph": "21", "winddirDegree": "308", "winddir16Point": "NW", "weatherCode": "116", "weatherIconUrl": [{"value": "http://cdn.worldweatheronline.com/images/wsymbols01_png_64/wsymbol_0002_sunny_intervals.png"}], "weatherDesc": [{"value": "Partly cloudy"}], "lang_fr": [{"value": "Partiellement nuageux"}], "precipMM": "0.0", "precipInches": "0.0", "humidity": "16", "visibility": "10", "visibilityMiles": "6", "pressure": "1013", "pressureInches": "30", "cloudcover": "2", "HeatIndexC": "39", "HeatIndexF": "102", "DewPointC": "8", "DewPointF": "46", "WindChillC": "39", "WindChillF": "102", "WindGustMiles": "15", "WindGustKmph": "24", "FeelsLikeC": "39", "FeelsLikeF": "102", "uvIndex": "9"}, {"time": "1700", "tempC": "36", "tempF": "98", "windspeedMiles": "12", "windspeedKmph": "19", "winddirDegree": "308", "winddir16Point": "NW", "weatherCode": "113", "weatherIconUrl": [{"value": "http://cdn.worldweatheronline.com/images/wsymbols01_png_64/wsymbol_0001_sunny.png"}], "weatherDesc": [{"value": "Sunny"}], "lang_fr": [{"value": "Ensoleillé"}], "precipMM": "0.0", "precipInches": "0.0", "humidity": "20", "visibility": "10", "visibilityMiles": "6", "pressure": "1014", "pressureInches": "30", "cloudcover": "1", "HeatIndexC": "36", "HeatIndexF": "96", "DewPointC": "9", "DewPointF": "48", "WindChillC": "36", "WindChillF": "98", "WindGustMiles": "14", "WindGustKmph": "22", "FeelsLikeC": "36", "FeelsLikeF": "96", "uvIndex": "9"}, {"time": "1800", "tempC": "34", "tempF": "93", "windspeedMiles": "11", "windspeedKmph": "17", "winddirDegree": "308", "winddir16Point": "NW", "weatherCode": "113", "weatherIconUrl": [{"value": "http://cdn.worldweatheronline.com/images/wsymbols01_png_64/wsymbol_0008_clear_sky_night.png"}], "weatherDesc": [{"value": "Clear"}], "lang_fr": [{"value": "Clair"}], "precipMM": "0.0", "precipInches": "0.0", "humidity": "24", "visibility": "10", "visibilityMiles": "6", "pressure": "1014", "pressureInches": "30", "cloudcover": "0", "HeatIndexC": "32", "HeatIndexF": "90", "DewPointC": "10", "DewPointF": "50", "WindChillC": "34", "WindChillF": "93", "WindGustMiles": "12", "WindGustKmph": "19", "FeelsLikeC": "32", "FeelsLikeF": "90", "uvIndex": "1"}, {"time": "1900", "tempC": "31", "tempF": "88", "windspeedMiles": "8", "windspeedKmph": "13", "winddirDegree": "308", "winddir16Point": "NW", "weatherCode": "113", "weatherIconUrl": [{"value": "http://cdn.worldweatheronline.com/images/wsymbols01_png_64/wsymbol_0008_clear_sky_night.png"}], "weatherDesc": [{"value": "Clear"}], "lang_fr": [{"value": "Clair"}], "precipMM": "0.0", "precipInches": "0.0", "humidity": "28", "visibility": "10", "visibilityMiles": "6", "pressure": "1015", "pressureInches": "30", "cloudcover": "3", "HeatIndexC": "30", "HeatIndexF": "87", "DewPointC": "10", "DewPointF": "51", "WindChillC": "31", "WindChillF": "88", "WindGustMiles": "10", "WindGustKmph": "16", "FeelsLikeC": "30", "FeelsLikeF": "87", "uvIndex": "1"}, {"time": "2000", "tempC": "29", "tempF": "84", "windspeedMiles": "5", "windspeedKmph": "8", "winddirDegree": "308", "winddir16Point": "NW", "weatherCode": "116", "weatherIconUrl": [{"value": "http://cdn.worldweatheronline.com/images/wsymbols01_png_64/wsymbol_0004_black_low_cloud.png"}], "weatherDesc": [{"value": "Partly cloudy"}], "lang_fr": [{"value": "Partiellement nuageux"}], "precipMM": "0.0", "precipInches": "0.0", "humidity": "33", "visibility": "10", "visibilityMiles": "6", "pressure": "1015", "pressureInches": "30", "cloudcover": "7", "HeatIndexC": "28", "HeatIndexF": "83", "DewPointC": "11", "DewPointF": "51", "WindChillC": "29", "WindChillF": "84", "WindGustMiles": "7", "WindGustKmph": "12", "FeelsLikeC": "28", "FeelsLikeF": "83", "uvIndex": "1"}, {"time": "2100", "tempC": "26", "tempF": "80", "windspeedMiles": "2", "windspeedKmph": "4", "winddirDegree": "307", "winddir16Point": "NW", "weatherCode": "116", "weatherIconUrl": [{"value": "http://cdn.worldweatheronline.com/images/wsymbols01_png_64/wsymbol_0004_black_low_cloud.png"}], "weatherDesc": [{"value": "Partly cloudy"}], "lang_fr": [{"value": "Partiellement nuageux"}], "precipMM": "0.0", "precipInches": "0.0", "humidity": "38", "visibility": "10", "visibilityMiles": "6", "pressure": "1016", "pressureInches": "30", "cloudcover": "10", "HeatIndexC": "26", "HeatIndexF": "79", "DewPointC": "11", "DewPointF": "51", "WindChillC": "26", "WindChillF": "80", "WindGustMiles": "5", "WindGustKmph": "8", "FeelsLikeC": "26", "FeelsLikeF": "79", "uvIndex": "1"}, {"time": "2200", "tempC": "26", "tempF": "79", "windspeedMiles": "3", "windspeedKmph": "4", "winddirDegree": "304", "winddir16Point": "NW", "weatherCode": "116", "weatherIconUrl": [{"value": "http://cdn.worldweatheronline.com/images/wsymbols01_png_64/wsymbol_0004_black_low_cloud.png"}], "weatherDesc": [{"value": "Partly cloudy"}], "lang_fr": [{"value": "Partiellement nuageux"}], "precipMM": "0.0", "precipInches": "0.0", "humidity": "38", "visibility": "10", "visibilityMiles": "6", "pressure": "1015", "pressureInches": "30", "cloudcover": "9", "HeatIndexC": "26", "HeatIndexF": "79", "DewPointC": "10", "DewPointF": "51", "WindChillC": "26", "WindChillF": "79", "WindGustMiles": "6", "WindGustKmph": "9", "FeelsLikeC": "26", "FeelsLikeF": "79", "uvIndex": "1"}, {"time": "2300", "tempC": "26", "tempF": "78", "windspeedMiles": "3", "windspeedKmph": "5", "winddirDegree": "301", "winddir16Point": "WNW", "weatherCode": "116", "weatherIconUrl": [{"value": "http://cdn.worldweatheronline.com/images/wsymbols01_png_64/wsymbol_0004_black_low_cloud.png"}], "weatherDesc": [{"value": "Partly cloudy"}], "lang_fr": [{"value": "Partiellement nuageux"}], "precipMM": "0.0", "precipInches": "0.0", "humidity": "38", "visibility": "10", "visibilityMiles": "6", "pressure": "1015", "pressureInches": "30", "cloudcover": "8", "HeatIndexC": "26", "HeatIndexF": "78", "DewPointC": "10", "DewPointF": "50", "WindChillC": "26", "WindChillF": "78", "WindGustMiles": "6", "WindGustKmph": "10", "FeelsLikeC": "26", "FeelsLikeF": "78", "uvIndex": "1"}]}]}}