{"data": {"request": [{"type": "City", "query": "Auserd, Western Sahara"}], "weather": [{"date": "2019-02-16", "astronomy": [{"sunrise": "08:28 AM", "sunset": "07:54 PM", "moonrise": "04:41 PM", "moonset": "05:28 AM", "moon_phase": "Waxing Gibbous", "moon_illumination": "78"}], "maxtempC": "24", "maxtempF": "75", "mintempC": "14", "mintempF": "57", "avgtempC": "19", "avgtempF": "66", "totalSnow_cm": "0.0", "sunHour": "11.3", "uvIndex": "5", "hourly": [{"time": "0", "tempC": "19", "tempF": "67", "windspeedMiles": "13", "windspeedKmph": "22", "winddirDegree": "330", "winddir16Point": "NNW", "weatherCode": "113", "weatherIconUrl": [{"value": "http://cdn.worldweatheronline.com/images/wsymbols01_png_64/wsymbol_0008_clear_sky_night.png"}], "weatherDesc": [{"value": "Clear"}], "lang_fr": [{"value": "Clair"}], "precipMM": "0.0", "precipInches": "0.0", "humidity": "27", "visibility": "10", "visibilityMiles": "6", "pressure": "1017", "pressureInches": "30", "cloudcover": "0", "HeatIndexC": "19", "HeatIndexF": "67", "DewPointC": "-0", "DewPointF": "31", "WindChillC": "19", "WindChillF": "67", "WindGustMiles": "22", "WindGustKmph": "35", "FeelsLikeC": "19", "FeelsLikeF": "67", "uvIndex": "1"}, {"time": "100", "tempC": "18", "tempF": "65", "windspeedMiles": "13", "windspeedKmph": "21", "winddirDegree": "339", "winddir16Point": "NNW", "weatherCode": "113", "weatherIconUrl": [{"value": "http://cdn.worldweatheronline.com/images/wsymbols01_png_64/wsymbol_0008_clear_sky_night.png"}], "weatherDesc": [{"value": "Clear"}], "lang_fr": [{"value": "Clair"}], "precipMM": "0.0", "precipInches": "0.0", "humidity": "38", "visibility": "10", "visibilityMiles": "6", "pressure": "1017", "pressureInches": "30", "cloudcover": "0", "HeatIndexC": "18", "HeatIndexF": "65", "DewPointC": "3", "DewPointF": "37", "WindChillC": "18", "WindChillF": "65", "WindGustMiles": "21", "WindGustKmph": "33", "FeelsLikeC": "18", "FeelsLikeF": "65", "uvIndex": "1"}, {"time": "200", "tempC": "17", "tempF": "62", "windspeedMiles": "13", "windspeedKmph": "21", "winddirDegree": "347", "winddir16Point": "NNW", "weatherCode": "113", "weatherIconUrl": [{"value": "http://cdn.worldweatheronline.com/images/wsymbols01_png_64/wsymbol_0008_clear_sky_night.png"}], "weatherDesc": [{"value": "Clear"}], "lang_fr": [{"value": "Clair"}], "precipMM": "0.0", "precipInches": "0.0", "humidity": "50", "visibility": "10", "visibilityMiles": "6", "pressure": "1017", "pressureInches": "30", "cloudcover": "0", "HeatIndexC": "17", "HeatIndexF": "62", "DewPointC": "6", "DewPointF": "42", "WindChillC": "17", "WindChillF": "62", "WindGustMiles": "20", "WindGustKmph": "32", "FeelsLikeC": "17", "FeelsLikeF": "62", "uvIndex": "1"}, {"time": "300", "tempC": "16", "tempF": "60", "windspeedMiles": "13", "windspeedKmph": "20", "winddirDegree": "356", "winddir16Point": "N", "weatherCode": "113", "weatherIconUrl": [{"value": "http://cdn.worldweatheronline.com/images/wsymbols01_png_64/wsymbol_0008_clear_sky_night.png"}], "weatherDesc": [{"value": "Clear"}], "lang_fr": [{"value": "Clair"}], "precipMM": "0.0", "precipInches": "0.0", "humidity": "61", "visibility": "10", "visibilityMiles": "6", "pressure": "1017", "pressureInches": "30", "cloudcover": "0", "HeatIndexC": "16", "HeatIndexF": "60", "DewPointC": "8", "DewPointF": "47", "WindChillC": "16", "WindChillF": "60", "WindGustMiles": "19", "WindGustKmph": "30", "FeelsLikeC": "16", "FeelsLikeF": "60", "uvIndex": "1"}, {"time": "400", "tempC": "15", "tempF": "59", "windspeedMiles": "12", "windspeedKmph": "19", "winddirDegree": "238", "winddir16Point": "WSW", "weatherCode": "113", "weatherIconUrl": [{"value": "http://cdn.worldweatheronline.com/images/wsymbols01_png_64/wsymbol_0008_clear_sky_night.png"}], "weatherDesc": [{"value": "Clear"}], "lang_fr": [{"value": "Clair"}], "precipMM": "0.0", "precipInches": "0.0", "humidity": "65", "visibility": "10", "visibilityMiles": "6", "pressure": "1017", "pressureInches": "30", "cloudcover": "0", "HeatIndexC": "15", "HeatIndexF": "59", "DewPointC": "9", "DewPointF": "48", "WindChillC": "15", "WindChillF": "58", "WindGustMiles": "18", "WindGustKmph": "29", "FeelsLikeC": "15", "FeelsLikeF": "58", "uvIndex": "1"}, {"time": "500", "tempC": "15", "tempF": "58", "windspeedMiles": "11", "windspeedKmph": "18", "winddirDegree": "119", "winddir16Point": "ESE", "weatherCode": "113", "weatherIconUrl": [{"value": "http://cdn.worldweatheronline.com/images/wsymbols01_png_64/wsymbol_0008_clear_sky_night.png"}], "weatherDesc": [{"value": "Clear"}], "lang_fr": [{"value": "Clair"}], "precipMM": "0.0", "precipInches": "0.0", "humidity": "70", "visibility": "10", "visibilityMiles": "6", "pressure": "1017", "pressureInches": "30", "cloudcover": "0", "HeatIndexC": "15", "HeatIndexF": "58", "DewPointC": "9", "DewPointF": "48", "WindChillC": "14", "WindChillF": "56", "WindGustMiles": "17", "WindGustKmph": "27", "FeelsLikeC": "14", "FeelsLikeF": "56", "uvIndex": "1"}, {"time": "600", "tempC": "14", "tempF": "57", "windspeedMiles": "11", "windspeedKmph": "17", "winddirDegree": "1", "winddir16Point": "N", "weatherCode": "113", "weatherIconUrl": [{"value": "http://cdn.worldweatheronline.com/images/wsymbols01_png_64/wsymbol_0001_sunny.png"}], "weatherDesc": [{"value": "Sunny"}], "lang_fr": [{"value": "Ensoleillé"}], "precipMM": "0.0", "precipInches": "0.0", "humidity": "74", "visibility": "10", "visibilityMiles": "6", "pressure": "1017", "pressureInches": "30", "cloudcover": "0", "HeatIndexC": "14", "HeatIndexF": "57", "DewPointC": "9", "DewPointF": "49", "WindChillC": "13", "WindChillF": "55", "WindGustMiles": "16", "WindGustKmph": "26", "FeelsLikeC": "13", "FeelsLikeF": "55", "uvIndex": "4"}, {"time": "700", "tempC": "14", "tempF": "58", "windspeedMiles": "12", "windspeedKmph": "19", "winddirDegree": "2", "winddir16Point": "N", "weatherCode": "113", "weatherIconUrl": [{"value": "http://cdn.worldweatheronline.com/images/wsymbols01_png_64/wsymbol_0001_sunny.png"}], "weatherDesc": [{"value": "Sunny"}], "lang_fr": [{"value": "Ensoleillé"}], "precipMM": "0.0", "precipInches": "0.0", "humidity": "71", "visibility": "10", "visibilityMiles": "6", "pressure": "1018", "pressureInches": "30", "cloudcover": "0", "HeatIndexC": "14", "HeatIndexF": "58", "DewPointC": "9", "DewPointF": "48", "WindChillC": "13", "WindChillF": "55", "WindGustMiles": "17", "WindGustKmph": "27", "FeelsLikeC": "13", "FeelsLikeF": "55", "uvIndex": "4"}, {"time": "800", "tempC": "15", "tempF": "58", "windspeedMiles": "13", "windspeedKmph": "21", "winddirDegree": "2", "winddir16Point": "N", "weatherCode": "113", "weatherIconUrl": [{"value": "http://cdn.worldweatheronline.com/images/wsymbols01_png_64/wsymbol_0001_sunny.png"}], "weatherDesc": [{"value": "Sunny"}], "lang_fr": [{"value": "Ensoleillé"}], "precipMM": "0.0", "precipInches": "0.0", "humidity": "67", "visibility": "10", "visibilityMiles": "6", "pressure": "1018", "pressureInches": "30", "cloudcover": "0", "HeatIndexC": "15", "HeatIndexF": "58", "DewPointC": "9", "DewPointF": "47", "WindChillC": "13", "WindChillF": "56", "WindGustMiles": "17", "WindGustKmph": "27", "FeelsLikeC": "13", "FeelsLikeF": "56", "uvIndex": "4"}, {"time": "900", "tempC": "15", "tempF": "59", "windspeedMiles": "14", "windspeedKmph": "23", "winddirDegree": "3", "winddir16Point": "N", "weatherCode": "113", "weatherIconUrl": [{"value": "http://cdn.worldweatheronline.com/images/wsymbols01_png_64/wsymbol_0001_sunny.png"}], "weatherDesc": [{"value": "Sunny"}], "lang_fr": [{"value": "Ensoleillé"}], "precipMM": "0.0", "precipInches": "0.0", "humidity": "64", "visibility": "10", "visibilityMiles": "6", "pressure": "1019", "pressureInches": "30", "cloudcover": "0", "HeatIndexC": "15", "HeatIndexF": "59", "DewPointC": "8", "DewPointF": "47", "WindChillC": "13", "WindChillF": "56", "WindGustMiles": "17", "WindGustKmph": "28", "FeelsLikeC": "13", "FeelsLikeF": "56", "uvIndex": "4"}, {"time": "1000", "tempC": "17", "tempF": "62", "windspeedMiles": "14", "windspeedKmph": "23", "winddirDegree": "3", "winddir16Point": "N", "weatherCode": "113", "weatherIconUrl": [{"value": "http://cdn.worldweatheronline.com/images/wsymbols01_png_64/wsymbol_0001_sunny.png"}], "weatherDesc": [{"value": "Sunny"}], "lang_fr": [{"value": "Ensoleillé"}], "precipMM": "0.0", "precipInches": "0.0", "humidity": "54", "visibility": "10", "visibilityMiles": "6", "pressure": "1019", "pressureInches": "30", "cloudcover": "0", "HeatIndexC": "17", "HeatIndexF": "62", "DewPointC": "7", "DewPointF": "44", "WindChillC": "16", "WindChillF": "60", "WindGustMiles": "17", "WindGustKmph": "28", "FeelsLikeC": "16", "FeelsLikeF": "60", "uvIndex": "5"}, {"time": "1100", "tempC": "19", "tempF": "66", "windspeedMiles": "15", "windspeedKmph": "23", "winddirDegree": "3", "winddir16Point": "N", "weatherCode": "113", "weatherIconUrl": [{"value": "http://cdn.worldweatheronline.com/images/wsymbols01_png_64/wsymbol_0001_sunny.png"}], "weatherDesc": [{"value": "Sunny"}], "lang_fr": [{"value": "Ensoleillé"}], "precipMM": "0.0", "precipInches": "0.0", "humidity": "44", "visibility": "10", "visibilityMiles": "6", "pressure": "1018", "pressureInches": "30", "cloudcover": "0", "HeatIndexC": "19", "HeatIndexF": "66", "DewPointC": "6", "DewPointF": "42", "WindChillC": "18", "WindChillF": "65", "WindGustMiles": "17", "WindGustKmph": "27", "FeelsLikeC": "18", "FeelsLikeF": "65", "uvIndex": "5"}, {"time": "1200", "tempC": "21", "tempF": "69", "windspeedMiles": "15", "windspeedKmph": "24", "winddirDegree": "3", "winddir16Point": "N", "weatherCode": "113", "weatherIconUrl": [{"value": "http://cdn.worldweatheronline.com/images/wsymbols01_png_64/wsymbol_0001_sunny.png"}], "weatherDesc": [{"value": "Sunny"}], "lang_fr": [{"value": "Ensoleillé"}], "precipMM": "0.0", "precipInches": "0.0", "humidity": "34", "visibility": "10", "visibilityMiles": "6", "pressure": "1018", "pressureInches": "30", "cloudcover": "0", "HeatIndexC": "21", "HeatIndexF": "69", "DewPointC": "4", "DewPointF": "40", "WindChillC": "21", "WindChillF": "69", "WindGustMiles": "17", "WindGustKmph": "27", "FeelsLikeC": "21", "FeelsLikeF": "69", "uvIndex": "6"}, {"time": "1300", "tempC": "22", "tempF": "71", "windspeedMiles": "15", "windspeedKmph": "24", "winddirDegree": "121", "winddir16Point": "ESE", "weatherCode": "113", "weatherIconUrl": [{"value": "http://cdn.worldweatheronline.com/images/wsymbols01_png_64/wsymbol_0001_sunny.png"}], "weatherDesc": [{"value": "Sunny"}], "lang_fr": [{"value": "Ensoleillé"}], "precipMM": "0.0", "precipInches": "0.0", "humidity": "30", "visibility": "10", "visibilityMiles": "6", "pressure": "1017", "pressureInches": "30", "cloudcover": "0", "HeatIndexC": "21", "HeatIndexF": "71", "DewPointC": "3", "DewPointF": "38", "WindChillC": "22", "WindChillF": "71", "WindGustMiles": "17", "WindGustKmph": "27", "FeelsLikeC": "22", "FeelsLikeF": "71", "uvIndex": "6"}, {"time": "1400", "tempC": "23", "tempF": "73", "windspeedMiles": "15", "windspeedKmph": "24", "winddirDegree": "239", "winddir16Point": "WSW", "weatherCode": "113", "weatherIconUrl": [{"value": "http://cdn.worldweatheronline.com/images/wsymbols01_png_64/wsymbol_0001_sunny.png"}], "weatherDesc": [{"value": "Sunny"}], "lang_fr": [{"value": "Ensoleillé"}], "precipMM": "0.0", "precipInches": "0.0", "humidity": "26", "visibility": "10", "visibilityMiles": "6", "pressure": "1017", "pressureInches": "30", "cloudcover": "0", "HeatIndexC": "22", "HeatIndexF": "72", "DewPointC": "2", "DewPointF": "36", "WindChillC": "23", "WindChillF": "73", "WindGustMiles": "17", "WindGustKmph": "27", "FeelsLikeC": "22", "FeelsLikeF": "72", "uvIndex": "6"}, {"time": "1500", "tempC": "24", "tempF": "75", "windspeedMiles": "15", "windspeedKmph": "23", "winddirDegree": "358", "winddir16Point": "N", "weatherCode": "113", "weatherIconUrl": [{"value": "http://cdn.worldweatheronline.com/images/wsymbols01_png_64/wsymbol_0001_sunny.png"}], "weatherDesc": [{"value": "Sunny"}], "lang_fr": [{"value": "Ensoleillé"}], "precipMM": "0.0", "precipInches": "0.0", "humidity": "22", "visibility": "10", "visibilityMiles": "6", "pressure": "1016", "pressureInches": "30", "cloudcover": "0", "HeatIndexC": "23", "HeatIndexF": "74", "DewPointC": "1", "DewPointF": "34", "WindChillC": "24", "WindChillF": "75", "WindGustMiles": "17", "WindGustKmph": "27", "FeelsLikeC": "23", "FeelsLikeF": "74", "uvIndex": "6"}, {"time": "1600", "tempC": "23", "tempF": "74", "windspeedMiles": "15", "windspeedKmph": "24", "winddirDegree": "358", "winddir16Point": "N", "weatherCode": "113", "weatherIconUrl": [{"value": "http://cdn.worldweatheronline.com/images/wsymbols01_png_64/wsymbol_0001_sunny.png"}], "weatherDesc": [{"value": "Sunny"}], "lang_fr": [{"value": "Ensoleillé"}], "precipMM": "0.0", "precipInches": "0.0", "humidity": "22", "visibility": "10", "visibilityMiles": "6", "pressure": "1016", "pressureInches": "30", "cloudcover": "0", "HeatIndexC": "23", "HeatIndexF": "74", "DewPointC": "1", "DewPointF": "33", "WindChillC": "23", "WindChillF": "74", "WindGustMiles": "17", "WindGustKmph": "28", "FeelsLikeC": "23", "FeelsLikeF": "74", "uvIndex": "6"}, {"time": "1700", "tempC": "23", "tempF": "73", "windspeedMiles": "15", "windspeedKmph": "24", "winddirDegree": "358", "winddir16Point": "N", "weatherCode": "113", "weatherIconUrl": [{"value": "http://cdn.worldweatheronline.com/images/wsymbols01_png_64/wsymbol_0001_sunny.png"}], "weatherDesc": [{"value": "Sunny"}], "lang_fr": [{"value": "Ensoleillé"}], "precipMM": "0.0", "precipInches": "0.0", "humidity": "23", "visibility": "10", "visibilityMiles": "6", "pressure": "1016", "pressureInches": "30", "cloudcover": "0", "HeatIndexC": "23", "HeatIndexF": "73", "DewPointC": "1", "DewPointF": "33", "WindChillC": "23", "WindChillF": "73", "WindGustMiles": "18", "WindGustKmph": "29", "FeelsLikeC": "23", "FeelsLikeF": "73", "uvIndex": "6"}, {"time": "1800", "tempC": "22", "tempF": "72", "windspeedMiles": "15", "windspeedKmph": "25", "winddirDegree": "359", "winddir16Point": "N", "weatherCode": "113", "weatherIconUrl": [{"value": "http://cdn.worldweatheronline.com/images/wsymbols01_png_64/wsymbol_0008_clear_sky_night.png"}], "weatherDesc": [{"value": "Clear"}], "lang_fr": [{"value": "Clair"}], "precipMM": "0.0", "precipInches": "0.0", "humidity": "23", "visibility": "10", "visibilityMiles": "6", "pressure": "1015", "pressureInches": "30", "cloudcover": "0", "HeatIndexC": "23", "HeatIndexF": "73", "DewPointC": "1", "DewPointF": "33", "WindChillC": "22", "WindChillF": "72", "WindGustMiles": "19", "WindGustKmph": "30", "FeelsLikeC": "23", "FeelsLikeF": "73", "uvIndex": "1"}, {"time": "1900", "tempC": "21", "tempF": "70", "windspeedMiles": "14", "windspeedKmph": "23", "winddirDegree": "241", "winddir16Point": "WSW", "weatherCode": "113", "weatherIconUrl": [{"value": "http://cdn.worldweatheronline.com/images/wsymbols01_png_64/wsymbol_0008_clear_sky_night.png"}], "weatherDesc": [{"value": "Clear"}], "lang_fr": [{"value": "Clair"}], "precipMM": "0.0", "precipInches": "0.0", "humidity": "28", "visibility": "10", "visibilityMiles": "6", "pressure": "1016", "pressureInches": "30", "cloudcover": "0", "HeatIndexC": "21", "HeatIndexF": "70", "DewPointC": "2", "DewPointF": "35", "WindChillC": "21", "WindChillF": "70", "WindGustMiles": "19", "WindGustKmph": "30", "FeelsLikeC": "21", "FeelsLikeF": "70", "uvIndex": "1"}, {"time": "2000", "tempC": "20", "tempF": "68", "windspeedMiles": "13", "windspeedKmph": "22", "winddirDegree": "124", "winddir16Point": "ESE", "weatherCode": "113", "weatherIconUrl": [{"value": "http://cdn.worldweatheronline.com/images/wsymbols01_png_64/wsymbol_0008_clear_sky_night.png"}], "weatherDesc": [{"value": "Clear"}], "lang_fr": [{"value": "Clair"}], "precipMM": "0.0", "precipInches": "0.0", "humidity": "33", "visibility": "10", "visibilityMiles": "6", "pressure": "1017", "pressureInches": "30", "cloudcover": "0", "HeatIndexC": "20", "HeatIndexF": "68", "DewPointC": "3", "DewPointF": "37", "WindChillC": "20", "WindChillF": "68", "WindGustMiles": "19", "WindGustKmph": "30", "FeelsLikeC": "20", "FeelsLikeF": "68", "uvIndex": "1"}, {"time": "2100", "tempC": "19", "tempF": "65", "windspeedMiles": "13", "windspeedKmph": "20", "winddirDegree": "6", "winddir16Point": "N", "weatherCode": "113", "weatherIconUrl": [{"value": "http://cdn.worldweatheronline.com/images/wsymbols01_png_64/wsymbol_0008_clear_sky_night.png"}], "weatherDesc": [{"value": "Clear"}], "lang_fr": [{"value": "Clair"}], "precipMM": "0.0", "precipInches": "0.0", "humidity": "37", "visibility": "10", "visibilityMiles": "6", "pressure": "1018", "pressureInches": "30", "cloudcover": "0", "HeatIndexC": "19", "HeatIndexF": "65", "DewPointC": "4", "DewPointF": "39", "WindChillC": "19", "WindChillF": "65", "WindGustMiles": "19", "WindGustKmph": "30", "FeelsLikeC": "19", "FeelsLikeF": "65", "uvIndex": "1"}, {"time": "2200", "tempC": "18", "tempF": "64", "windspeedMiles": "13", "windspeedKmph": "20", "winddirDegree": "7", "winddir16Point": "N", "weatherCode": "113", "weatherIconUrl": [{"value": "http://cdn.worldweatheronline.com/images/wsymbols01_png_64/wsymbol_0008_clear_sky_night.png"}], "weatherDesc": [{"value": "Clear"}], "lang_fr": [{"value": "Clair"}], "precipMM": "0.0", "precipInches": "0.0", "humidity": "40", "visibility": "10", "visibilityMiles": "6", "pressure": "1018", "pressureInches": "30", "cloudcover": "0", "HeatIndexC": "18", "HeatIndexF": "64", "DewPointC": "4", "DewPointF": "39", "WindChillC": "18", "WindChillF": "64", "WindGustMiles": "19", "WindGustKmph": "31", "FeelsLikeC": "18", "FeelsLikeF": "64", "uvIndex": "1"}, {"time": "2300", "tempC": "17", "tempF": "63", "windspeedMiles": "13", "windspeedKmph": "20", "winddirDegree": "8", "winddir16Point": "N", "weatherCode": "113", "weatherIconUrl": [{"value": "http://cdn.worldweatheronline.com/images/wsymbols01_png_64/wsymbol_0008_clear_sky_night.png"}], "weatherDesc": [{"value": "Clear"}], "lang_fr": [{"value": "Clair"}], "precipMM": "0.0", "precipInches": "0.0", "humidity": "42", "visibility": "10", "visibilityMiles": "6", "pressure": "1018", "pressureInches": "30", "cloudcover": "0", "HeatIndexC": "17", "HeatIndexF": "63", "DewPointC": "4", "DewPointF": "40", "WindChillC": "17", "WindChillF": "63", "WindGustMiles": "20", "WindGustKmph": "31", "FeelsLikeC": "17", "FeelsLikeF": "63", "uvIndex": "1"}]}]}}