{"data": {"request": [{"type": "City", "query": "Taroudannt, Morocco"}], "weather": [{"date": "2020-01-26", "astronomy": [{"sunrise": "08:30 AM", "sunset": "07:06 PM", "moonrise": "09:42 AM", "moonset": "08:40 PM", "moon_phase": "New Moon", "moon_illumination": "8"}], "maxtempC": "20", "maxtempF": "68", "mintempC": "7", "mintempF": "45", "avgtempC": "15", "avgtempF": "59", "totalSnow_cm": "0.0", "sunHour": "10.8", "uvIndex": "4", "hourly": [{"time": "0", "tempC": "9", "tempF": "48", "windspeedMiles": "2", "windspeedKmph": "3", "winddirDegree": "18", "winddir16Point": "NNE", "weatherCode": "116", "weatherIconUrl": [{"value": "http://cdn.worldweatheronline.com/images/wsymbols01_png_64/wsymbol_0004_black_low_cloud.png"}], "weatherDesc": [{"value": "Partly cloudy"}], "lang_fr": [{"value": "Partiellement nuageux"}], "precipMM": "0.0", "precipInches": "0.0", "humidity": "90", "visibility": "10", "visibilityMiles": "6", "pressure": "1024", "pressureInches": "30", "cloudcover": "26", "HeatIndexC": "9", "HeatIndexF": "48", "DewPointC": "7", "DewPointF": "45", "WindChillC": "9", "WindChillF": "49", "WindGustMiles": "4", "WindGustKmph": "7", "FeelsLikeC": "9", "FeelsLikeF": "49", "uvIndex": "1"}, {"time": "100", "tempC": "9", "tempF": "48", "windspeedMiles": "2", "windspeedKmph": "3", "winddirDegree": "30", "winddir16Point": "NNE", "weatherCode": "116", "weatherIconUrl": [{"value": "http://cdn.worldweatheronline.com/images/wsymbols01_png_64/wsymbol_0004_black_low_cloud.png"}], "weatherDesc": [{"value": "Partly cloudy"}], "lang_fr": [{"value": "Partiellement nuageux"}], "precipMM": "0.0", "precipInches": "0.0", "humidity": "90", "visibility": "10", "visibilityMiles": "6", "pressure": "1024", "pressureInches": "30", "cloudcover": "34", "HeatIndexC": "9", "HeatIndexF": "48", "DewPointC": "7", "DewPointF": "45", "WindChillC": "9", "WindChillF": "48", "WindGustMiles": "4", "WindGustKmph": "7", "FeelsLikeC": "9", "FeelsLikeF": "48", "uvIndex": "1"}, {"time": "200", "tempC": "8", "tempF": "47", "windspeedMiles": "2", "windspeedKmph": "3", "winddirDegree": "42", "winddir16Point": "NE", "weatherCode": "116", "weatherIconUrl": [{"value": "http://cdn.worldweatheronline.com/images/wsymbols01_png_64/wsymbol_0004_black_low_cloud.png"}], "weatherDesc": [{"value": "Partly cloudy"}], "lang_fr": [{"value": "Partiellement nuageux"}], "precipMM": "0.0", "precipInches": "0.0", "humidity": "91", "visibility": "10", "visibilityMiles": "6", "pressure": "1024", "pressureInches": "30", "cloudcover": "42", "HeatIndexC": "8", "HeatIndexF": "47", "DewPointC": "7", "DewPointF": "45", "WindChillC": "9", "WindChillF": "47", "WindGustMiles": "4", "WindGustKmph": "6", "FeelsLikeC": "9", "FeelsLikeF": "47", "uvIndex": "1"}, {"time": "300", "tempC": "8", "tempF": "47", "windspeedMiles": "2", "windspeedKmph": "3", "winddirDegree": "54", "winddir16Point": "NE", "weatherCode": "116", "weatherIconUrl": [{"value": "http://cdn.worldweatheronline.com/images/wsymbols01_png_64/wsymbol_0004_black_low_cloud.png"}], "weatherDesc": [{"value": "Partly cloudy"}], "lang_fr": [{"value": "Partiellement nuageux"}], "precipMM": "0.0", "precipInches": "0.0", "humidity": "91", "visibility": "10", "visibilityMiles": "6", "pressure": "1024", "pressureInches": "30", "cloudcover": "50", "HeatIndexC": "8", "HeatIndexF": "47", "DewPointC": "7", "DewPointF": "44", "WindChillC": "8", "WindChillF": "47", "WindGustMiles": "4", "WindGustKmph": "6", "FeelsLikeC": "8", "FeelsLikeF": "47", "uvIndex": "1"}, {"time": "400", "tempC": "8", "tempF": "46", "windspeedMiles": "2", "windspeedKmph": "4", "winddirDegree": "58", "winddir16Point": "ENE", "weatherCode": "116", "weatherIconUrl": [{"value": "http://cdn.worldweatheronline.com/images/wsymbols01_png_64/wsymbol_0004_black_low_cloud.png"}], "weatherDesc": [{"value": "Partly cloudy"}], "lang_fr": [{"value": "Partiellement nuageux"}], "precipMM": "0.0", "precipInches": "0.0", "humidity": "91", "visibility": "10", "visibilityMiles": "6", "pressure": "1023", "pressureInches": "30", "cloudcover": "39", "HeatIndexC": "8", "HeatIndexF": "46", "DewPointC": "6", "DewPointF": "44", "WindChillC": "7", "WindChillF": "45", "WindGustMiles": "5", "WindGustKmph": "8", "FeelsLikeC": "7", "FeelsLikeF": "45", "uvIndex": "1"}, {"time": "500", "tempC": "7", "tempF": "45", "windspeedMiles": "3", "windspeedKmph": "5", "winddirDegree": "63", "winddir16Point": "ENE", "weatherCode": "116", "weatherIconUrl": [{"value": "http://cdn.worldweatheronline.com/images/wsymbols01_png_64/wsymbol_0004_black_low_cloud.png"}], "weatherDesc": [{"value": "Partly cloudy"}], "lang_fr": [{"value": "Partiellement nuageux"}], "precipMM": "0.0", "precipInches": "0.0", "humidity": "91", "visibility": "10", "visibilityMiles": "6", "pressure": "1023", "pressureInches": "30", "cloudcover": "28", "HeatIndexC": "7", "HeatIndexF": "45", "DewPointC": "6", "DewPointF": "43", "WindChillC": "7", "WindChillF": "44", "WindGustMiles": "7", "WindGustKmph": "11", "FeelsLikeC": "7", "FeelsLikeF": "44", "uvIndex": "1"}, {"time": "600", "tempC": "7", "tempF": "45", "windspeedMiles": "4", "windspeedKmph": "6", "winddirDegree": "68", "winddir16Point": "ENE", "weatherCode": "116", "weatherIconUrl": [{"value": "http://cdn.worldweatheronline.com/images/wsymbols01_png_64/wsymbol_0002_sunny_intervals.png"}], "weatherDesc": [{"value": "Partly cloudy"}], "lang_fr": [{"value": "Partiellement nuageux"}], "precipMM": "0.0", "precipInches": "0.0", "humidity": "91", "visibility": "10", "visibilityMiles": "6", "pressure": "1023", "pressureInches": "30", "cloudcover": "18", "HeatIndexC": "7", "HeatIndexF": "45", "DewPointC": "6", "DewPointF": "42", "WindChillC": "6", "WindChillF": "43", "WindGustMiles": "8", "WindGustKmph": "13", "FeelsLikeC": "6", "FeelsLikeF": "43", "uvIndex": "3"}, {"time": "700", "tempC": "9", "tempF": "48", "windspeedMiles": "4", "windspeedKmph": "7", "winddirDegree": "65", "winddir16Point": "ENE", "weatherCode": "116", "weatherIconUrl": [{"value": "http://cdn.worldweatheronline.com/images/wsymbols01_png_64/wsymbol_0002_sunny_intervals.png"}], "weatherDesc": [{"value": "Partly cloudy"}], "lang_fr": [{"value": "Partiellement nuageux"}], "precipMM": "0.0", "precipInches": "0.0", "humidity": "85", "visibility": "10", "visibilityMiles": "6", "pressure": "1024", "pressureInches": "30", "cloudcover": "12", "HeatIndexC": "9", "HeatIndexF": "48", "DewPointC": "6", "DewPointF": "43", "WindChillC": "8", "WindChillF": "46", "WindGustMiles": "8", "WindGustKmph": "13", "FeelsLikeC": "8", "FeelsLikeF": "46", "uvIndex": "3"}, {"time": "800", "tempC": "11", "tempF": "51", "windspeedMiles": "5", "windspeedKmph": "8", "winddirDegree": "62", "winddir16Point": "ENE", "weatherCode": "113", "weatherIconUrl": [{"value": "http://cdn.worldweatheronline.com/images/wsymbols01_png_64/wsymbol_0001_sunny.png"}], "weatherDesc": [{"value": "Sunny"}], "lang_fr": [{"value": "Ensoleillé"}], "precipMM": "0.0", "precipInches": "0.0", "humidity": "79", "visibility": "10", "visibilityMiles": "6", "pressure": "1024", "pressureInches": "30", "cloudcover": "6", "HeatIndexC": "11", "HeatIndexF": "51", "DewPointC": "7", "DewPointF": "45", "WindChillC": "10", "WindChillF": "49", "WindGustMiles": "8", "WindGustKmph": "12", "FeelsLikeC": "10", "FeelsLikeF": "49", "uvIndex": "4"}, {"time": "900", "tempC": "12", "tempF": "54", "windspeedMiles": "6", "windspeedKmph": "9", "winddirDegree": "59", "winddir16Point": "ENE", "weatherCode": "113", "weatherIconUrl": [{"value": "http://cdn.worldweatheronline.com/images/wsymbols01_png_64/wsymbol_0001_sunny.png"}], "weatherDesc": [{"value": "Sunny"}], "lang_fr": [{"value": "Ensoleillé"}], "precipMM": "0.0", "precipInches": "0.0", "humidity": "73", "visibility": "10", "visibilityMiles": "6", "pressure": "1025", "pressureInches": "30", "cloudcover": "0", "HeatIndexC": "12", "HeatIndexF": "54", "DewPointC": "8", "DewPointF": "46", "WindChillC": "12", "WindChillF": "53", "WindGustMiles": "8", "WindGustKmph": "12", "FeelsLikeC": "12", "FeelsLikeF": "53", "uvIndex": "4"}, {"time": "1000", "tempC": "14", "tempF": "57", "windspeedMiles": "5", "windspeedKmph": "8", "winddirDegree": "67", "winddir16Point": "ENE", "weatherCode": "113", "weatherIconUrl": [{"value": "http://cdn.worldweatheronline.com/images/wsymbols01_png_64/wsymbol_0001_sunny.png"}], "weatherDesc": [{"value": "Sunny"}], "lang_fr": [{"value": "Ensoleillé"}], "precipMM": "0.0", "precipInches": "0.0", "humidity": "64", "visibility": "10", "visibilityMiles": "6", "pressure": "1025", "pressureInches": "30", "cloudcover": "0", "HeatIndexC": "14", "HeatIndexF": "57", "DewPointC": "7", "DewPointF": "44", "WindChillC": "14", "WindChillF": "56", "WindGustMiles": "6", "WindGustKmph": "10", "FeelsLikeC": "14", "FeelsLikeF": "56", "uvIndex": "4"}, {"time": "1100", "tempC": "16", "tempF": "61", "windspeedMiles": "4", "windspeedKmph": "7", "winddirDegree": "76", "winddir16Point": "ENE", "weatherCode": "113", "weatherIconUrl": [{"value": "http://cdn.worldweatheronline.com/images/wsymbols01_png_64/wsymbol_0001_sunny.png"}], "weatherDesc": [{"value": "Sunny"}], "lang_fr": [{"value": "Ensoleillé"}], "precipMM": "0.0", "precipInches": "0.0", "humidity": "54", "visibility": "10", "visibilityMiles": "6", "pressure": "1024", "pressureInches": "30", "cloudcover": "0", "HeatIndexC": "16", "HeatIndexF": "61", "DewPointC": "6", "DewPointF": "43", "WindChillC": "16", "WindChillF": "60", "WindGustMiles": "5", "WindGustKmph": "8", "FeelsLikeC": "16", "FeelsLikeF": "60", "uvIndex": "5"}, {"time": "1200", "tempC": "18", "tempF": "64", "windspeedMiles": "4", "windspeedKmph": "6", "winddirDegree": "85", "winddir16Point": "E", "weatherCode": "113", "weatherIconUrl": [{"value": "http://cdn.worldweatheronline.com/images/wsymbols01_png_64/wsymbol_0001_sunny.png"}], "weatherDesc": [{"value": "Sunny"}], "lang_fr": [{"value": "Ensoleillé"}], "precipMM": "0.0", "precipInches": "0.0", "humidity": "44", "visibility": "10", "visibilityMiles": "6", "pressure": "1024", "pressureInches": "30", "cloudcover": "0", "HeatIndexC": "18", "HeatIndexF": "64", "DewPointC": "5", "DewPointF": "42", "WindChillC": "18", "WindChillF": "64", "WindGustMiles": "4", "WindGustKmph": "6", "FeelsLikeC": "18", "FeelsLikeF": "64", "uvIndex": "5"}, {"time": "1300", "tempC": "18", "tempF": "65", "windspeedMiles": "4", "windspeedKmph": "6", "winddirDegree": "140", "winddir16Point": "SE", "weatherCode": "113", "weatherIconUrl": [{"value": "http://cdn.worldweatheronline.com/images/wsymbols01_png_64/wsymbol_0001_sunny.png"}], "weatherDesc": [{"value": "Sunny"}], "lang_fr": [{"value": "Ensoleillé"}], "precipMM": "0.0", "precipInches": "0.0", "humidity": "39", "visibility": "10", "visibilityMiles": "6", "pressure": "1024", "pressureInches": "30", "cloudcover": "0", "HeatIndexC": "18", "HeatIndexF": "65", "DewPointC": "4", "DewPointF": "39", "WindChillC": "18", "WindChillF": "65", "WindGustMiles": "5", "WindGustKmph": "7", "FeelsLikeC": "18", "FeelsLikeF": "65", "uvIndex": "5"}, {"time": "1400", "tempC": "19", "tempF": "67", "windspeedMiles": "4", "windspeedKmph": "7", "winddirDegree": "196", "winddir16Point": "SSW", "weatherCode": "113", "weatherIconUrl": [{"value": "http://cdn.worldweatheronline.com/images/wsymbols01_png_64/wsymbol_0001_sunny.png"}], "weatherDesc": [{"value": "Sunny"}], "lang_fr": [{"value": "Ensoleillé"}], "precipMM": "0.0", "precipInches": "0.0", "humidity": "35", "visibility": "10", "visibilityMiles": "6", "pressure": "1023", "pressureInches": "30", "cloudcover": "0", "HeatIndexC": "19", "HeatIndexF": "67", "DewPointC": "3", "DewPointF": "37", "WindChillC": "19", "WindChillF": "67", "WindGustMiles": "5", "WindGustKmph": "8", "FeelsLikeC": "19", "FeelsLikeF": "67", "uvIndex": "5"}, {"time": "1500", "tempC": "20", "tempF": "68", "windspeedMiles": "5", "windspeedKmph": "8", "winddirDegree": "252", "winddir16Point": "WSW", "weatherCode": "113", "weatherIconUrl": [{"value": "http://cdn.worldweatheronline.com/images/wsymbols01_png_64/wsymbol_0001_sunny.png"}], "weatherDesc": [{"value": "Sunny"}], "lang_fr": [{"value": "Ensoleillé"}], "precipMM": "0.0", "precipInches": "0.0", "humidity": "30", "visibility": "10", "visibilityMiles": "6", "pressure": "1022", "pressureInches": "30", "cloudcover": "0", "HeatIndexC": "20", "HeatIndexF": "68", "DewPointC": "2", "DewPointF": "35", "WindChillC": "20", "WindChillF": "68", "WindGustMiles": "6", "WindGustKmph": "9", "FeelsLikeC": "20", "FeelsLikeF": "68", "uvIndex": "6"}, {"time": "1600", "tempC": "19", "tempF": "66", "windspeedMiles": "7", "windspeedKmph": "11", "winddirDegree": "252", "winddir16Point": "WSW", "weatherCode": "113", "weatherIconUrl": [{"value": "http://cdn.worldweatheronline.com/images/wsymbols01_png_64/wsymbol_0001_sunny.png"}], "weatherDesc": [{"value": "Sunny"}], "lang_fr": [{"value": "Ensoleillé"}], "precipMM": "0.0", "precipInches": "0.0", "humidity": "38", "visibility": "10", "visibilityMiles": "6", "pressure": "1022", "pressureInches": "30", "cloudcover": "0", "HeatIndexC": "20", "HeatIndexF": "69", "DewPointC": "3", "DewPointF": "37", "WindChillC": "19", "WindChillF": "66", "WindGustMiles": "10", "WindGustKmph": "16", "FeelsLikeC": "19", "FeelsLikeF": "66", "uvIndex": "5"}, {"time": "1700", "tempC": "18", "tempF": "64", "windspeedMiles": "8", "windspeedKmph": "13", "winddirDegree": "253", "winddir16Point": "WSW", "weatherCode": "113", "weatherIconUrl": [{"value": "http://cdn.worldweatheronline.com/images/wsymbols01_png_64/wsymbol_0001_sunny.png"}], "weatherDesc": [{"value": "Sunny"}], "lang_fr": [{"value": "Ensoleillé"}], "precipMM": "0.0", "precipInches": "0.0", "humidity": "46", "visibility": "10", "visibilityMiles": "6", "pressure": "1022", "pressureInches": "30", "cloudcover": "0", "HeatIndexC": "21", "HeatIndexF": "69", "DewPointC": "4", "DewPointF": "40", "WindChillC": "18", "WindChillF": "64", "WindGustMiles": "14", "WindGustKmph": "23", "FeelsLikeC": "18", "FeelsLikeF": "64", "uvIndex": "5"}, {"time": "1800", "tempC": "17", "tempF": "63", "windspeedMiles": "10", "windspeedKmph": "16", "winddirDegree": "254", "winddir16Point": "WSW", "weatherCode": "113", "weatherIconUrl": [{"value": "http://cdn.worldweatheronline.com/images/wsymbols01_png_64/wsymbol_0008_clear_sky_night.png"}], "weatherDesc": [{"value": "Clear"}], "lang_fr": [{"value": "Clair"}], "precipMM": "0.0", "precipInches": "0.0", "humidity": "55", "visibility": "10", "visibilityMiles": "6", "pressure": "1023", "pressureInches": "30", "cloudcover": "0", "HeatIndexC": "21", "HeatIndexF": "70", "DewPointC": "6", "DewPointF": "42", "WindChillC": "17", "WindChillF": "63", "WindGustMiles": "19", "WindGustKmph": "30", "FeelsLikeC": "17", "FeelsLikeF": "63", "uvIndex": "1"}, {"time": "1900", "tempC": "16", "tempF": "60", "windspeedMiles": "7", "windspeedKmph": "12", "winddirDegree": "263", "winddir16Point": "W", "weatherCode": "113", "weatherIconUrl": [{"value": "http://cdn.worldweatheronline.com/images/wsymbols01_png_64/wsymbol_0008_clear_sky_night.png"}], "weatherDesc": [{"value": "Clear"}], "lang_fr": [{"value": "Clair"}], "precipMM": "0.0", "precipInches": "0.0", "humidity": "65", "visibility": "10", "visibilityMiles": "6", "pressure": "1023", "pressureInches": "30", "cloudcover": "0", "HeatIndexC": "20", "HeatIndexF": "67", "DewPointC": "7", "DewPointF": "44", "WindChillC": "16", "WindChillF": "60", "WindGustMiles": "13", "WindGustKmph": "22", "FeelsLikeC": "16", "FeelsLikeF": "60", "uvIndex": "1"}, {"time": "2000", "tempC": "14", "tempF": "58", "windspeedMiles": "4", "windspeedKmph": "7", "winddirDegree": "273", "winddir16Point": "W", "weatherCode": "113", "weatherIconUrl": [{"value": "http://cdn.worldweatheronline.com/images/wsymbols01_png_64/wsymbol_0008_clear_sky_night.png"}], "weatherDesc": [{"value": "Clear"}], "lang_fr": [{"value": "Clair"}], "precipMM": "0.0", "precipInches": "0.0", "humidity": "75", "visibility": "10", "visibilityMiles": "6", "pressure": "1024", "pressureInches": "30", "cloudcover": "0", "HeatIndexC": "18", "HeatIndexF": "65", "DewPointC": "8", "DewPointF": "46", "WindChillC": "14", "WindChillF": "58", "WindGustMiles": "8", "WindGustKmph": "14", "FeelsLikeC": "14", "FeelsLikeF": "58", "uvIndex": "1"}, {"time": "2100", "tempC": "13", "tempF": "55", "windspeedMiles": "2", "windspeedKmph": "3", "winddirDegree": "282", "winddir16Point": "WNW", "weatherCode": "113", "weatherIconUrl": [{"value": "http://cdn.worldweatheronline.com/images/wsymbols01_png_64/wsymbol_0008_clear_sky_night.png"}], "weatherDesc": [{"value": "Clear"}], "lang_fr": [{"value": "Clair"}], "precipMM": "0.0", "precipInches": "0.0", "humidity": "86", "visibility": "10", "visibilityMiles": "6", "pressure": "1025", "pressureInches": "30", "cloudcover": "0", "HeatIndexC": "17", "HeatIndexF": "63", "DewPointC": "9", "DewPointF": "48", "WindChillC": "13", "WindChillF": "55", "WindGustMiles": "3", "WindGustKmph": "5", "FeelsLikeC": "13", "FeelsLikeF": "55", "uvIndex": "1"}, {"time": "2200", "tempC": "12", "tempF": "53", "windspeedMiles": "2", "windspeedKmph": "4", "winddirDegree": "211", "winddir16Point": "SSW", "weatherCode": "113", "weatherIconUrl": [{"value": "http://cdn.worldweatheronline.com/images/wsymbols01_png_64/wsymbol_0008_clear_sky_night.png"}], "weatherDesc": [{"value": "Clear"}], "lang_fr": [{"value": "Clair"}], "precipMM": "0.0", "precipInches": "0.0", "humidity": "85", "visibility": "10", "visibilityMiles": "6", "pressure": "1025", "pressureInches": "30", "cloudcover": "0", "HeatIndexC": "15", "HeatIndexF": "58", "DewPointC": "8", "DewPointF": "47", "WindChillC": "12", "WindChillF": "53", "WindGustMiles": "5", "WindGustKmph": "8", "FeelsLikeC": "12", "FeelsLikeF": "53", "uvIndex": "1"}, {"time": "2300", "tempC": "11", "tempF": "51", "windspeedMiles": "3", "windspeedKmph": "5", "winddirDegree": "139", "winddir16Point": "SE", "weatherCode": "113", "weatherIconUrl": [{"value": "http://cdn.worldweatheronline.com/images/wsymbols01_png_64/wsymbol_0008_clear_sky_night.png"}], "weatherDesc": [{"value": "Clear"}], "lang_fr": [{"value": "Clair"}], "precipMM": "0.0", "precipInches": "0.0", "humidity": "85", "visibility": "10", "visibilityMiles": "6", "pressure": "1025", "pressureInches": "30", "cloudcover": "0", "HeatIndexC": "12", "HeatIndexF": "54", "DewPointC": "8", "DewPointF": "46", "WindChillC": "10", "WindChillF": "51", "WindGustMiles": "6", "WindGustKmph": "10", "FeelsLikeC": "10", "FeelsLikeF": "51", "uvIndex": "1"}]}]}}