{"data": {"request": [{"type": "City", "query": "El Jadida, Morocco"}], "weather": [{"date": "2019-06-21", "astronomy": [{"sunrise": "06:25 AM", "sunset": "08:46 PM", "moonrise": "No moonrise", "moonset": "10:01 AM", "moon_phase": "Full Moon", "moon_illumination": "75"}], "maxtempC": "22", "maxtempF": "72", "mintempC": "18", "mintempF": "64", "avgtempC": "21", "avgtempF": "69", "totalSnow_cm": "0.0", "sunHour": "11.6", "uvIndex": "6", "hourly": [{"time": "0", "tempC": "19", "tempF": "66", "windspeedMiles": "13", "windspeedKmph": "21", "winddirDegree": "27", "winddir16Point": "NNE", "weatherCode": "113", "weatherIconUrl": [{"value": "http://cdn.worldweatheronline.com/images/wsymbols01_png_64/wsymbol_0008_clear_sky_night.png"}], "weatherDesc": [{"value": "Clear"}], "lang_fr": [{"value": "Clair"}], "precipMM": "0.0", "precipInches": "0.0", "humidity": "82", "visibility": "10", "visibilityMiles": "6", "pressure": "1019", "pressureInches": "30", "cloudcover": "2", "HeatIndexC": "19", "HeatIndexF": "66", "DewPointC": "16", "DewPointF": "61", "WindChillC": "19", "WindChillF": "66", "WindGustMiles": "21", "WindGustKmph": "33", "FeelsLikeC": "19", "FeelsLikeF": "66", "uvIndex": "1"}, {"time": "100", "tempC": "19", "tempF": "66", "windspeedMiles": "13", "windspeedKmph": "21", "winddirDegree": "29", "winddir16Point": "NNE", "weatherCode": "113", "weatherIconUrl": [{"value": "http://cdn.worldweatheronline.com/images/wsymbols01_png_64/wsymbol_0008_clear_sky_night.png"}], "weatherDesc": [{"value": "Clear"}], "lang_fr": [{"value": "Clair"}], "precipMM": "0.0", "precipInches": "0.0", "humidity": "83", "visibility": "10", "visibilityMiles": "6", "pressure": "1019", "pressureInches": "30", "cloudcover": "10", "HeatIndexC": "19", "HeatIndexF": "66", "DewPointC": "16", "DewPointF": "60", "WindChillC": "19", "WindChillF": "66", "WindGustMiles": "20", "WindGustKmph": "32", "FeelsLikeC": "19", "FeelsLikeF": "66", "uvIndex": "1"}, {"time": "200", "tempC": "18", "tempF": "65", "windspeedMiles": "13", "windspeedKmph": "21", "winddirDegree": "30", "winddir16Point": "NNE", "weatherCode": "113", "weatherIconUrl": [{"value": "http://cdn.worldweatheronline.com/images/wsymbols01_png_64/wsymbol_0008_clear_sky_night.png"}], "weatherDesc": [{"value": "Clear"}], "lang_fr": [{"value": "Clair"}], "precipMM": "0.0", "precipInches": "0.0", "humidity": "84", "visibility": "10", "visibilityMiles": "6", "pressure": "1018", "pressureInches": "30", "cloudcover": "17", "HeatIndexC": "18", "HeatIndexF": "65", "DewPointC": "15", "DewPointF": "60", "WindChillC": "18", "WindChillF": "65", "WindGustMiles": "19", "WindGustKmph": "31", "FeelsLikeC": "18", "FeelsLikeF": "65", "uvIndex": "1"}, {"time": "300", "tempC": "18", "tempF": "64", "windspeedMiles": "13", "windspeedKmph": "20", "winddirDegree": "31", "winddir16Point": "NNE", "weatherCode": "113", "weatherIconUrl": [{"value": "http://cdn.worldweatheronline.com/images/wsymbols01_png_64/wsymbol_0008_clear_sky_night.png"}], "weatherDesc": [{"value": "Clear"}], "lang_fr": [{"value": "Clair"}], "precipMM": "0.0", "precipInches": "0.0", "humidity": "84", "visibility": "10", "visibilityMiles": "6", "pressure": "1018", "pressureInches": "30", "cloudcover": "25", "HeatIndexC": "18", "HeatIndexF": "64", "DewPointC": "15", "DewPointF": "59", "WindChillC": "18", "WindChillF": "64", "WindGustMiles": "19", "WindGustKmph": "30", "FeelsLikeC": "18", "FeelsLikeF": "64", "uvIndex": "1"}, {"time": "400", "tempC": "18", "tempF": "64", "windspeedMiles": "13", "windspeedKmph": "21", "winddirDegree": "27", "winddir16Point": "NNE", "weatherCode": "113", "weatherIconUrl": [{"value": "http://cdn.worldweatheronline.com/images/wsymbols01_png_64/wsymbol_0008_clear_sky_night.png"}], "weatherDesc": [{"value": "Clear"}], "lang_fr": [{"value": "Clair"}], "precipMM": "0.0", "precipInches": "0.0", "humidity": "85", "visibility": "10", "visibilityMiles": "6", "pressure": "1018", "pressureInches": "30", "cloudcover": "33", "HeatIndexC": "18", "HeatIndexF": "64", "DewPointC": "15", "DewPointF": "59", "WindChillC": "18", "WindChillF": "64", "WindGustMiles": "19", "WindGustKmph": "31", "FeelsLikeC": "18", "FeelsLikeF": "64", "uvIndex": "1"}, {"time": "500", "tempC": "18", "tempF": "64", "windspeedMiles": "14", "windspeedKmph": "22", "winddirDegree": "24", "winddir16Point": "NNE", "weatherCode": "116", "weatherIconUrl": [{"value": "http://cdn.worldweatheronline.com/images/wsymbols01_png_64/wsymbol_0004_black_low_cloud.png"}], "weatherDesc": [{"value": "Partly cloudy"}], "lang_fr": [{"value": "Partiellement nuageux"}], "precipMM": "0.0", "precipInches": "0.0", "humidity": "85", "visibility": "10", "visibilityMiles": "6", "pressure": "1018", "pressureInches": "30", "cloudcover": "42", "HeatIndexC": "18", "HeatIndexF": "64", "DewPointC": "15", "DewPointF": "59", "WindChillC": "18", "WindChillF": "64", "WindGustMiles": "19", "WindGustKmph": "31", "FeelsLikeC": "18", "FeelsLikeF": "64", "uvIndex": "1"}, {"time": "600", "tempC": "18", "tempF": "64", "windspeedMiles": "14", "windspeedKmph": "23", "winddirDegree": "20", "winddir16Point": "NNE", "weatherCode": "116", "weatherIconUrl": [{"value": "http://cdn.worldweatheronline.com/images/wsymbols01_png_64/wsymbol_0002_sunny_intervals.png"}], "weatherDesc": [{"value": "Partly cloudy"}], "lang_fr": [{"value": "Partiellement nuageux"}], "precipMM": "0.0", "precipInches": "0.0", "humidity": "86", "visibility": "10", "visibilityMiles": "6", "pressure": "1018", "pressureInches": "30", "cloudcover": "51", "HeatIndexC": "18", "HeatIndexF": "64", "DewPointC": "15", "DewPointF": "59", "WindChillC": "18", "WindChillF": "64", "WindGustMiles": "20", "WindGustKmph": "32", "FeelsLikeC": "18", "FeelsLikeF": "64", "uvIndex": "5"}, {"time": "700", "tempC": "19", "tempF": "65", "windspeedMiles": "15", "windspeedKmph": "23", "winddirDegree": "21", "winddir16Point": "NNE", "weatherCode": "116", "weatherIconUrl": [{"value": "http://cdn.worldweatheronline.com/images/wsymbols01_png_64/wsymbol_0002_sunny_intervals.png"}], "weatherDesc": [{"value": "Partly cloudy"}], "lang_fr": [{"value": "Partiellement nuageux"}], "precipMM": "0.0", "precipInches": "0.0", "humidity": "80", "visibility": "10", "visibilityMiles": "6", "pressure": "1018", "pressureInches": "30", "cloudcover": "46", "HeatIndexC": "19", "HeatIndexF": "65", "DewPointC": "15", "DewPointF": "59", "WindChillC": "19", "WindChillF": "65", "WindGustMiles": "19", "WindGustKmph": "31", "FeelsLikeC": "19", "FeelsLikeF": "65", "uvIndex": "5"}, {"time": "800", "tempC": "19", "tempF": "67", "windspeedMiles": "15", "windspeedKmph": "24", "winddirDegree": "21", "winddir16Point": "NNE", "weatherCode": "116", "weatherIconUrl": [{"value": "http://cdn.worldweatheronline.com/images/wsymbols01_png_64/wsymbol_0002_sunny_intervals.png"}], "weatherDesc": [{"value": "Partly cloudy"}], "lang_fr": [{"value": "Partiellement nuageux"}], "precipMM": "0.0", "precipInches": "0.0", "humidity": "75", "visibility": "10", "visibilityMiles": "6", "pressure": "1018", "pressureInches": "30", "cloudcover": "40", "HeatIndexC": "19", "HeatIndexF": "67", "DewPointC": "15", "DewPointF": "59", "WindChillC": "19", "WindChillF": "67", "WindGustMiles": "18", "WindGustKmph": "29", "FeelsLikeC": "19", "FeelsLikeF": "67", "uvIndex": "5"}, {"time": "900", "tempC": "20", "tempF": "69", "windspeedMiles": "15", "windspeedKmph": "24", "winddirDegree": "22", "winddir16Point": "NNE", "weatherCode": "116", "weatherIconUrl": [{"value": "http://cdn.worldweatheronline.com/images/wsymbols01_png_64/wsymbol_0002_sunny_intervals.png"}], "weatherDesc": [{"value": "Partly cloudy"}], "lang_fr": [{"value": "Partiellement nuageux"}], "precipMM": "0.0", "precipInches": "0.0", "humidity": "70", "visibility": "10", "visibilityMiles": "6", "pressure": "1018", "pressureInches": "30", "cloudcover": "35", "HeatIndexC": "20", "HeatIndexF": "69", "DewPointC": "15", "DewPointF": "58", "WindChillC": "20", "WindChillF": "69", "WindGustMiles": "17", "WindGustKmph": "28", "FeelsLikeC": "20", "FeelsLikeF": "69", "uvIndex": "6"}, {"time": "1000", "tempC": "21", "tempF": "70", "windspeedMiles": "15", "windspeedKmph": "25", "winddirDegree": "20", "winddir16Point": "NNE", "weatherCode": "116", "weatherIconUrl": [{"value": "http://cdn.worldweatheronline.com/images/wsymbols01_png_64/wsymbol_0002_sunny_intervals.png"}], "weatherDesc": [{"value": "Partly cloudy"}], "lang_fr": [{"value": "Partiellement nuageux"}], "precipMM": "0.0", "precipInches": "0.0", "humidity": "67", "visibility": "10", "visibilityMiles": "6", "pressure": "1018", "pressureInches": "30", "cloudcover": "23", "HeatIndexC": "22", "HeatIndexF": "71", "DewPointC": "14", "DewPointF": "58", "WindChillC": "21", "WindChillF": "70", "WindGustMiles": "18", "WindGustKmph": "28", "FeelsLikeC": "21", "FeelsLikeF": "70", "uvIndex": "6"}, {"time": "1100", "tempC": "22", "tempF": "71", "windspeedMiles": "16", "windspeedKmph": "25", "winddirDegree": "17", "winddir16Point": "NNE", "weatherCode": "113", "weatherIconUrl": [{"value": "http://cdn.worldweatheronline.com/images/wsymbols01_png_64/wsymbol_0001_sunny.png"}], "weatherDesc": [{"value": "Sunny"}], "lang_fr": [{"value": "Ensoleillé"}], "precipMM": "0.0", "precipInches": "0.0", "humidity": "64", "visibility": "10", "visibilityMiles": "6", "pressure": "1018", "pressureInches": "30", "cloudcover": "12", "HeatIndexC": "23", "HeatIndexF": "74", "DewPointC": "14", "DewPointF": "58", "WindChillC": "22", "WindChillF": "71", "WindGustMiles": "18", "WindGustKmph": "29", "FeelsLikeC": "22", "FeelsLikeF": "71", "uvIndex": "6"}, {"time": "1200", "tempC": "22", "tempF": "72", "windspeedMiles": "16", "windspeedKmph": "26", "winddirDegree": "15", "winddir16Point": "NNE", "weatherCode": "113", "weatherIconUrl": [{"value": "http://cdn.worldweatheronline.com/images/wsymbols01_png_64/wsymbol_0001_sunny.png"}], "weatherDesc": [{"value": "Sunny"}], "lang_fr": [{"value": "Ensoleillé"}], "precipMM": "0.0", "precipInches": "0.0", "humidity": "61", "visibility": "10", "visibilityMiles": "6", "pressure": "1018", "pressureInches": "30", "cloudcover": "0", "HeatIndexC": "25", "HeatIndexF": "76", "DewPointC": "14", "DewPointF": "58", "WindChillC": "22", "WindChillF": "72", "WindGustMiles": "19", "WindGustKmph": "30", "FeelsLikeC": "25", "FeelsLikeF": "76", "uvIndex": "6"}, {"time": "1300", "tempC": "22", "tempF": "72", "windspeedMiles": "17", "windspeedKmph": "27", "winddirDegree": "12", "winddir16Point": "NNE", "weatherCode": "113", "weatherIconUrl": [{"value": "http://cdn.worldweatheronline.com/images/wsymbols01_png_64/wsymbol_0001_sunny.png"}], "weatherDesc": [{"value": "Sunny"}], "lang_fr": [{"value": "Ensoleillé"}], "precipMM": "0.0", "precipInches": "0.0", "humidity": "62", "visibility": "10", "visibilityMiles": "6", "pressure": "1017", "pressureInches": "30", "cloudcover": "0", "HeatIndexC": "25", "HeatIndexF": "76", "DewPointC": "14", "DewPointF": "58", "WindChillC": "22", "WindChillF": "72", "WindGustMiles": "20", "WindGustKmph": "32", "FeelsLikeC": "25", "FeelsLikeF": "76", "uvIndex": "6"}, {"time": "1400", "tempC": "22", "tempF": "72", "windspeedMiles": "18", "windspeedKmph": "29", "winddirDegree": "9", "winddir16Point": "N", "weatherCode": "113", "weatherIconUrl": [{"value": "http://cdn.worldweatheronline.com/images/wsymbols01_png_64/wsymbol_0001_sunny.png"}], "weatherDesc": [{"value": "Sunny"}], "lang_fr": [{"value": "Ensoleillé"}], "precipMM": "0.0", "precipInches": "0.0", "humidity": "63", "visibility": "10", "visibilityMiles": "6", "pressure": "1016", "pressureInches": "30", "cloudcover": "0", "HeatIndexC": "25", "HeatIndexF": "76", "DewPointC": "15", "DewPointF": "59", "WindChillC": "22", "WindChillF": "72", "WindGustMiles": "21", "WindGustKmph": "33", "FeelsLikeC": "25", "FeelsLikeF": "76", "uvIndex": "6"}, {"time": "1500", "tempC": "22", "tempF": "72", "windspeedMiles": "19", "windspeedKmph": "30", "winddirDegree": "5", "winddir16Point": "N", "weatherCode": "113", "weatherIconUrl": [{"value": "http://cdn.worldweatheronline.com/images/wsymbols01_png_64/wsymbol_0001_sunny.png"}], "weatherDesc": [{"value": "Sunny"}], "lang_fr": [{"value": "Ensoleillé"}], "precipMM": "0.0", "precipInches": "0.0", "humidity": "65", "visibility": "10", "visibilityMiles": "6", "pressure": "1016", "pressureInches": "30", "cloudcover": "0", "HeatIndexC": "25", "HeatIndexF": "76", "DewPointC": "15", "DewPointF": "59", "WindChillC": "22", "WindChillF": "72", "WindGustMiles": "22", "WindGustKmph": "35", "FeelsLikeC": "25", "FeelsLikeF": "76", "uvIndex": "6"}, {"time": "1600", "tempC": "21", "tempF": "71", "windspeedMiles": "19", "windspeedKmph": "30", "winddirDegree": "8", "winddir16Point": "N", "weatherCode": "113", "weatherIconUrl": [{"value": "http://cdn.worldweatheronline.com/images/wsymbols01_png_64/wsymbol_0001_sunny.png"}], "weatherDesc": [{"value": "Sunny"}], "lang_fr": [{"value": "Ensoleillé"}], "precipMM": "0.0", "precipInches": "0.0", "humidity": "67", "visibility": "10", "visibilityMiles": "6", "pressure": "1016", "pressureInches": "30", "cloudcover": "0", "HeatIndexC": "23", "HeatIndexF": "74", "DewPointC": "15", "DewPointF": "59", "WindChillC": "21", "WindChillF": "71", "WindGustMiles": "22", "WindGustKmph": "35", "FeelsLikeC": "21", "FeelsLikeF": "71", "uvIndex": "6"}, {"time": "1700", "tempC": "21", "tempF": "70", "windspeedMiles": "19", "windspeedKmph": "30", "winddirDegree": "11", "winddir16Point": "NNE", "weatherCode": "113", "weatherIconUrl": [{"value": "http://cdn.worldweatheronline.com/images/wsymbols01_png_64/wsymbol_0001_sunny.png"}], "weatherDesc": [{"value": "Sunny"}], "lang_fr": [{"value": "Ensoleillé"}], "precipMM": "0.0", "precipInches": "0.0", "humidity": "69", "visibility": "10", "visibilityMiles": "6", "pressure": "1016", "pressureInches": "30", "cloudcover": "0", "HeatIndexC": "22", "HeatIndexF": "71", "DewPointC": "15", "DewPointF": "59", "WindChillC": "21", "WindChillF": "70", "WindGustMiles": "22", "WindGustKmph": "35", "FeelsLikeC": "21", "FeelsLikeF": "70", "uvIndex": "6"}, {"time": "1800", "tempC": "20", "tempF": "69", "windspeedMiles": "19", "windspeedKmph": "30", "winddirDegree": "14", "winddir16Point": "NNE", "weatherCode": "113", "weatherIconUrl": [{"value": "http://cdn.worldweatheronline.com/images/wsymbols01_png_64/wsymbol_0008_clear_sky_night.png"}], "weatherDesc": [{"value": "Clear"}], "lang_fr": [{"value": "Clair"}], "precipMM": "0.0", "precipInches": "0.0", "humidity": "71", "visibility": "10", "visibilityMiles": "6", "pressure": "1016", "pressureInches": "30", "cloudcover": "0", "HeatIndexC": "20", "HeatIndexF": "69", "DewPointC": "15", "DewPointF": "59", "WindChillC": "20", "WindChillF": "69", "WindGustMiles": "22", "WindGustKmph": "35", "FeelsLikeC": "20", "FeelsLikeF": "69", "uvIndex": "1"}, {"time": "1900", "tempC": "20", "tempF": "68", "windspeedMiles": "18", "windspeedKmph": "29", "winddirDegree": "14", "winddir16Point": "NNE", "weatherCode": "113", "weatherIconUrl": [{"value": "http://cdn.worldweatheronline.com/images/wsymbols01_png_64/wsymbol_0008_clear_sky_night.png"}], "weatherDesc": [{"value": "Clear"}], "lang_fr": [{"value": "Clair"}], "precipMM": "0.0", "precipInches": "0.0", "humidity": "74", "visibility": "10", "visibilityMiles": "6", "pressure": "1016", "pressureInches": "30", "cloudcover": "0", "HeatIndexC": "20", "HeatIndexF": "68", "DewPointC": "15", "DewPointF": "59", "WindChillC": "20", "WindChillF": "68", "WindGustMiles": "23", "WindGustKmph": "36", "FeelsLikeC": "20", "FeelsLikeF": "68", "uvIndex": "1"}, {"time": "2000", "tempC": "19", "tempF": "66", "windspeedMiles": "17", "windspeedKmph": "28", "winddirDegree": "15", "winddir16Point": "NNE", "weatherCode": "113", "weatherIconUrl": [{"value": "http://cdn.worldweatheronline.com/images/wsymbols01_png_64/wsymbol_0008_clear_sky_night.png"}], "weatherDesc": [{"value": "Clear"}], "lang_fr": [{"value": "Clair"}], "precipMM": "0.0", "precipInches": "0.0", "humidity": "76", "visibility": "10", "visibilityMiles": "6", "pressure": "1017", "pressureInches": "30", "cloudcover": "0", "HeatIndexC": "19", "HeatIndexF": "66", "DewPointC": "15", "DewPointF": "59", "WindChillC": "19", "WindChillF": "66", "WindGustMiles": "23", "WindGustKmph": "38", "FeelsLikeC": "19", "FeelsLikeF": "66", "uvIndex": "1"}, {"time": "2100", "tempC": "19", "tempF": "65", "windspeedMiles": "17", "windspeedKmph": "27", "winddirDegree": "15", "winddir16Point": "NNE", "weatherCode": "113", "weatherIconUrl": [{"value": "http://cdn.worldweatheronline.com/images/wsymbols01_png_64/wsymbol_0008_clear_sky_night.png"}], "weatherDesc": [{"value": "Clear"}], "lang_fr": [{"value": "Clair"}], "precipMM": "0.0", "precipInches": "0.0", "humidity": "79", "visibility": "10", "visibilityMiles": "6", "pressure": "1017", "pressureInches": "30", "cloudcover": "0", "HeatIndexC": "19", "HeatIndexF": "65", "DewPointC": "15", "DewPointF": "59", "WindChillC": "19", "WindChillF": "65", "WindGustMiles": "24", "WindGustKmph": "39", "FeelsLikeC": "19", "FeelsLikeF": "65", "uvIndex": "1"}, {"time": "2200", "tempC": "18", "tempF": "65", "windspeedMiles": "16", "windspeedKmph": "26", "winddirDegree": "18", "winddir16Point": "NNE", "weatherCode": "113", "weatherIconUrl": [{"value": "http://cdn.worldweatheronline.com/images/wsymbols01_png_64/wsymbol_0008_clear_sky_night.png"}], "weatherDesc": [{"value": "Clear"}], "lang_fr": [{"value": "Clair"}], "precipMM": "0.0", "precipInches": "0.0", "humidity": "81", "visibility": "10", "visibilityMiles": "6", "pressure": "1017", "pressureInches": "30", "cloudcover": "0", "HeatIndexC": "18", "HeatIndexF": "65", "DewPointC": "15", "DewPointF": "59", "WindChillC": "18", "WindChillF": "65", "WindGustMiles": "24", "WindGustKmph": "38", "FeelsLikeC": "18", "FeelsLikeF": "65", "uvIndex": "1"}, {"time": "2300", "tempC": "18", "tempF": "64", "windspeedMiles": "16", "windspeedKmph": "25", "winddirDegree": "21", "winddir16Point": "NNE", "weatherCode": "113", "weatherIconUrl": [{"value": "http://cdn.worldweatheronline.com/images/wsymbols01_png_64/wsymbol_0008_clear_sky_night.png"}], "weatherDesc": [{"value": "Clear"}], "lang_fr": [{"value": "Clair"}], "precipMM": "0.0", "precipInches": "0.0", "humidity": "83", "visibility": "10", "visibilityMiles": "6", "pressure": "1017", "pressureInches": "30", "cloudcover": "0", "HeatIndexC": "18", "HeatIndexF": "64", "DewPointC": "15", "DewPointF": "59", "WindChillC": "18", "WindChillF": "64", "WindGustMiles": "23", "WindGustKmph": "37", "FeelsLikeC": "18", "FeelsLikeF": "64", "uvIndex": "1"}]}]}}